Workbook
Name INTEXON: #REF!
Name RUBROS: '[1]B.D.'!$A$3:$C$8

Sheet Cuadro
B1: POSICIÓN DE CAJA ENE - JUNIO 2026
C2: Q1 (ENE-MAR) | D2: ABR | E2: MAY | F2: JUN | G2: ENE-JUNIO TOTAL
A3: x | B3: SALDO INICIAL DEL PERIODO | C3: =+'Detalle S10_Junio 2026'!O5 -> 213970.45 | D3: =+C13 -> 1214667.4 | E3: =+D13 -> 11226.4 | F3: =+E13 -> 47528.47 | G3: =+C3 -> 213970.45
B4: ENTRADAS DE CAJA
A5: a | B5: COBROS A CLIENTES / FACTURAS | C5: =+'Detalle S10_Junio 2026'!O86 -> 5560371.2 | D5: =+'Detalle S10_Junio 2026'!O676 -> 147028 | E5: =+'Detalle S10_Junio 2026'!O814 -> 449918.21 | F5: =+'Detalle S10_Junio 2026'!O990 -> 1249284.4 | G5: =SUM(C5:F5) -> 7406601.8
A6: b | B6: ANTICIPOS Y OTROS INGRESOS | C6: =+'Detalle S10_Junio 2026'!O96 -> 774938.87 | D6: =+'Detalle S10_Junio 2026'!O679 -> 213085.26 | E6: =+'Detalle S10_Junio 2026'!O822 -> 854089.05 | F6: =+'Detalle S10_Junio 2026'!O995 -> 233685.99 | G6: =SUM(C6:F6) -> 2075799.2
A7: a + b | B7: TOTAL ENTRADAS | C7: =SUM(C5:C6) -> 6335310 | D7: =SUM(D5:D6) -> 360113.26 | E7: =SUM(E5:E6) -> 1304007.3 | F7: =SUM(F5:F6) -> 1482970.4 | G7: =SUM(G5:G6) -> 9482400.9
B8: SALIDAS DE CAJA
A9: c | B9: REMUNERACIONES Y HONORARIOS (LOCADORES) | C9: =-+'Detalle S10_Junio 2026'!O139 -> 835295.83 | D9: =-+'Detalle S10_Junio 2026'!O695 -> 275321.89 | E9: =-+'Detalle S10_Junio 2026'!O841 -> 405879.14 | F9: =-'Detalle S10_Junio 2026'!O1075 -> 479140.47 | G9: =SUM(C9:F9) -> 1995637.3
A10: d | B10: PROVEEDORES, ARRIENDO, SERVICIOS Y OTROS | C10: =-+'Detalle S10_Junio 2026'!O631 -> 3124544.2 | D10: =-+'Detalle S10_Junio 2026'!O793 -> 820967.4 | E10: =-+'Detalle S10_Junio 2026'!O958 -> 693222.29 | F10: =-'Detalle S10_Junio 2026'!O1147 -> 767445.91 | G10: =SUM(C10:F10) -> 5406179.8
A11: e | B11: SUNAT / IMPUESTOS | C11: =-+'Detalle S10_Junio 2026'!O662 -> 1374773 | D11: =-+'Detalle S10_Junio 2026'!O803 -> 467265 | E11: =-+'Detalle S10_Junio 2026'!O968 -> 168603.76 | F11: =-'Detalle S10_Junio 2026'!O1167 -> 277542.16 | G11: =SUM(C11:F11) -> 2288183.9
A12: c + d + e | B12: TOTAL SALIDAS | C12: =SUM(C9:C11) -> 5334613.1 | D12: =SUM(D9:D11) -> 1563554.3 | E12: =SUM(E9:E11) -> 1267705.2 | F12: =SUM(F9:F11) -> 1524128.5 | G12: =SUM(G9:G11) -> 9690001.1
A13: z | B13: SALDO FINAL | C13: =+C3+C7-C12 -> 1214667.4 | D13: =+D3+D7-D12 -> 11226.4 | E13: =+E3+E7-E12 -> 47528.47 | F13: =+F3+F7-F12 -> 6370.3 | G13: =+G3+G7-G12 -> 6370.3
C17: SALIDAS | D17: ENTRADAS | E17: NETO
B18: CMO | C18: 2818347.4 | D18: 886628 | E18: -1931719.4
B19: AMERICANA | C19: 28000 | E19: -28000
B20: VC | C20: 566408 | E20: -566408
B21: ENGEREDE | C21: 8911 | E21: -8911
B22: ICYS | D22: 289100 | E22: 289100
B23: RY | C23: 215936 | D23: 955402 | E23: 739466
B24: OTROS ACREEDORES | C24: 1768576 | D24: -55630 | E24: -1824206
C25: 5406178.4 | D25: 2075500 | E25: -3330678.4
D26: 3330678.4

Sheet  cta 10
B2: INTEGRAL CONSULTORES
B3: Al 31 de Mayo de 2026
B5: CAJA Y BANCOS
C6: TC Compra | D6: 3.403
B7: DESCRIPCION | C7: US$ | D7: S/
B8: Total 10100021 Caja Chica MN | D8: 2000 | E8: no la tomamos para reporte
B9: Total 10410013 BBVA CONTINENTAL MN | D9: 1100.52
B10: Total 10410014 BBVA CONTINENTAL ME | C10: 1548.57 | D10: =+C10*D6 -> 5269.7837
B11: Total 10710021 BANCO NACIÓN - CTA DETRACCION | D11: 0
B12: SALDO AL 30 DE SETIEMBRE | D12: =SUM(D8:D11) -> 8370.3037 | E12: =+D11+D10+D9 -> 6370.3037 | F12: Importe S10
L60: =+L48+L56+L59+L51+L53 -> 0
M141: =14899454.51-M140 -> 14899455

Sheet Detalle S10_Junio 2026
A1: Item | B1: Cuenta Contable | C1: RUC Socio de Negocio | D1: Socio de Negocio | E1: Procedencia | F1: N° Asiento | G1: Libro | H1: Mes | I1: Periodo Contable | J1: Fecha de Transacción | K1: N° Documento | L1: N° Documento Pago | M1: MO | N1: Saldo Origen | O1: Saldo ( S/ ) | P1: Observación Documento | Q1: Observación | R1: Año | S1: F.Emisión
A2: o | B2: 10410013 BBVA CONTINENTAL MN | E2: 16. Asiento de Apertura | F2: 0000000001 | G2: Libro Diario | I2: 202600 Apertura 2026 | J2: 01/01/2026 | M2: S/ | N2: 121320.92 | O2: 121321.12 | P2: Asiento de Apertura | Q2: Asiento de Apertura | R2: 2026 | S2: 01/01/2026
A3: o | B3: 10710021 BANCO NACION - CTA DETRACCION | E3: 16. Asiento de Apertura | F3: 0000000001 | G3: Libro Diario | I3: 202600 Apertura 2026 | J3: 01/01/2026 | M3: S/ | N3: 91070 | O3: 91070 | P3: Asiento de Apertura | Q3: Asiento de Apertura | R3: 2026 | S3: 01/01/2026
A4: o | B4: 10410014 BBVA CONTINENTAL ME | E4: 16. Asiento de Apertura | F4: 0000000001 | G4: Libro Diario | I4: 202600 Apertura 2026 | J4: 01/01/2026 | M4: U$ | N4: 470.04 | O4: 1579.33 | P4: Asiento de Apertura | Q4: Asiento de Apertura | R4: 2026 | S4: 01/01/2026
A5: Total o | O5: =SUBTOTAL(9,O2:O4) -> 213970.45
A6: a | B6: 10410013 BBVA CONTINENTAL MN | C6: 20613390996 | D6: CONSORCIO HEALTH BERNALES | E6: 02. Transferencia a cuenta bancaria | F6: 0000001823 | G6: Caja y Bancos | H6: 46023 | I6: 202601 Enero 2026 | J6: 23/01/2026 | K6: FE E001-00000016 | L6: FE E001-00000016 | M6: S/ | N6: 320360.5 | O6: 320360.5 | P6: SERVICIO DE ASESORIA INTEGRAL EN LA ADMINISTRACION CONTRACTUAL PARA EL PROCESO: DISEÑO CONSTRUCCION Y EQUIPAMIENTO DEL NUEVO HOSPITAL NACIONAL SERGIO BERNALES, LOCALIDAD DE COLLIQUE, DISTRITO DE COMAS, PROVINCIA DE LIMA - ANTICIPO | Q6: COBRANZA DE FACTURA E001-16 | R6: 2026 | S6: 30/12/2024
A7: a | B7: 10410013 BBVA CONTINENTAL MN | C7: 20608830392 | D7: CONSORCIO STILER - RIPCONCIV - TECNOEDIL | E7: 02. Transferencia a cuenta bancaria | F7: 0000001820 | G7: Caja y Bancos | H7: 46023 | I7: 202601 Enero 2026 | J7: 24/01/2026 | K7: FE E001-00000267 | L7: FE E001-00000267 | M7: S/ | N7: 252483.54 | O7: 252483.54 | P7: SERVICIO DE ACOMPANAMIENTO Y ASESORIA TECNICO-LEGAL Y GESTIÓN DE RECLAMO PARA LA ORDEN DE CAMBIO 3 EN EL PROYECTO: MEJORAMIENTO DE LA CAPACIDAD RESOLUTIVA DE LOS SERVICIOS DE SALUD DEL HOSPITAL ANTONIO LORENA NIVEL III - CUSCO ETAPA 2. - OBS: CUOTA 13 DE 115 | Q7: COBRANZA DE FACTURA E001-267 | R7: 2026 | S7: 05/01/2026
A8: a | B8: 10410013 BBVA CONTINENTAL MN | C8: 20614395789 | D8: CONSORCIO SALUD HUANCA SANCOS II | E8: 02. Transferencia a cuenta bancaria | F8: 0000001811 | G8: Caja y Bancos | H8: 46023 | I8: 202601 Enero 2026 | J8: 15/01/2026 | K8: FE E001-00000138 | L8: FE E001-00000138 | M8: S/ | N8: 191834.46 | O8: 191834.46 | P8: SERVICIO DE GERENCIAMIENTO TECNICO CONTRACTUAL EN EL PROYECTO: MEJORAMIENTO DE LOS SERVICIOS DEL ESTABLECIMIENTO DE SALUD ESTRATEGICOS HUANCA SANCOS, DISTRITO DE SANCOS - PROVINCIA DE HUANCA SANCOS -DEPARTAMENTO DE AYACUCHO. | Q8: COBRANZA DE FACTURA E001-138 | R8: 2026 | S8: 31/07/2025
A9: a | B9: 10410013 BBVA CONTINENTAL MN | C9: 20607900052 | D9: CONSORCIO SAN MIGUEL | E9: 02. Transferencia a cuenta bancaria | F9: 0000001814 | G9: Caja y Bancos | H9: 46023 | I9: 202601 Enero 2026 | J9: 19/01/2026 | K9: FE E001-00000257 | L9: FE E001-00000257 | M9: S/ | N9: 165229.55 | O9: 165229.55 | P9: SERVICIO DE ASESORIA TECNICO LEGAL ESPECIALIZADA EN ADMINISTRACION CONTRACTUAL EN EL PROY:AMPLIACION Y MEJORAMIENTO DE SISTEMAS AGUA POTABLE Y ALCANTARILLADO EN SECTORES 311,313,330,310,312,314,300,307,319,324 Y 301,DE SJM,VMT Y VES-ETAPA 1 FRENTE 2 - VALORIZACION DE MAYORES GASTOS GENERALES VARIABLES- AMPLIACION DE PLAZO N°28. | Q9: COBRANZA DE FACTURA E001-257 | R9: 2026 | S9: 16/12/2025
A10: a | B10: 10410013 BBVA CONTINENTAL MN | C10: 20513250445 | D10: INMAC PERU S.A.C. | E10: 02. Transferencia a cuenta bancaria | F10: 0000001806 | G10: Caja y Bancos | H10: 46023 | I10: 202601 Enero 2026 | J10: 08/01/2026 | K10: FE E001-00000266 | L10: FE E001-00000266 | M10: S/ | N10: 139577.18 | O10: 139577.18 | P10: SERVICIOS TECNICO-LEGALES QUE COMPRENDEN LA ASESORIA Y PATROCINIO EN LA GESTION DE CONTROVERSIAS FRENTE A LA ANIN EN PROYECTO CHICAMA. | Q10: COBRANZA DE FACTURA E001-266 | R10: 2026 | S10: 31/12/2025
A11: a | B11: 10710021 BANCO NACION - CTA DETRACCION | C11: 20517562158 | D11: CONSTRUCTORA & INMOBILIARIA SAGITARIO Y ASOCIADOS S.A.C. - SAGITARIO & ASOCIADOS S.A.C. | E11: 02. Transferencia a cuenta bancaria | F11: 0000001865 | G11: Caja y Bancos | H11: 46023 | I11: 202601 Enero 2026 | J11: 09/01/2026 | K11: FE E001-00000194 | L11: FE E001-00000194 | M11: S/ | N11: 2124 | O11: 2124 | P11: SERVICIO DE ACOMPANAMIENTO Y ASESORIA TECNICO-LEGAL EN EL PROYECTO: EJECUCION DEL SALDO DE OBRA:MEJORAMIENTO DE LOS SERVICIOS DE SALUD DEL CENTRO DE SALUD MACHUPICCHU,DISTRITO DE MACHUPICCHU,PROVINCIA DE URUBAMBA,DEPARTAMENTO DE CUSCO.CUI 2343148. ACORDE CON ADENDA N° 01 AL CONTRATO N° 12-2024-MACHU. | Q11: Transferencia a Cuenta Bancaria | R11: 2026 | S11: 15/10/2025
A12: a | B12: 10710021 BANCO NACION - CTA DETRACCION | C12: 20517562158 | D12: CONSTRUCTORA & INMOBILIARIA SAGITARIO Y ASOCIADOS S.A.C. - SAGITARIO & ASOCIADOS S.A.C. | E12: 02. Transferencia a cuenta bancaria | F12: 0000001913 | G12: Caja y Bancos | H12: 46023 | I12: 202601 Enero 2026 | J12: 09/01/2026 | K12: FE E001-00000247 | L12: FE E001-00000247 | M12: S/ | N12: 2124 | O12: 2124 | P12: SERVICIO DE ACOMPANAMIENTO Y ASESORIA TECNICO-LEGAL EN EL PROYECTO: EJECUCION DEL SALDO DE OBRA:MEJORAMIENTO DE LOS SERVICIOS DE SALUD DEL CENTRO DE SALUD MACHUPICCHU,DISTRITO DE MACHUPICCHU,PROVINCIA DE URUBAMBA,DEPARTAMENTO DE CUSCO.CUI 2343148. ACORDE CON ADENDA N° 01 AL CONTRATO N° 12-2024-MACHU. | Q12: Transferencia a Cuenta Bancaria | R12: 2026 | S12: 15/12/2025
A13: a | B13: 10710021 BANCO NACION - CTA DETRACCION | C13: 20517562158 | D13: CONSTRUCTORA & INMOBILIARIA SAGITARIO Y ASOCIADOS S.A.C. - SAGITARIO & ASOCIADOS S.A.C. | E13: 02. Transferencia a cuenta bancaria | F13: 0000001862 | G13: Caja y Bancos | H13: 46023 | I13: 202601 Enero 2026 | J13: 09/01/2026 | K13: FE E001-00000193 | L13: FE E001-00000193 | M13: S/ | N13: 2124 | O13: 2124 | P13: SERVICIO DE ACOMPANAMIENTO Y ASESORIA TECNICO-LEGAL EN EL PROYECTO: MEJORAMIENTO Y AMPLIACION DE LOS SERVICIOS DE SALUD DEL ESTABLECIMIENTO DE SALUD TUPAC AMARU,DISTRITO DE TUPAC AMARU,PROV PISCO,DEPARTAMENTO DE ICA. ACORDE CON ADENDA N° 01 AL CONTRATO N° 11-2024-TUPAC. | Q13: Transferencia a Cuenta Bancaria | R13: 2026 | S13: 15/10/2025
A14: a | B14: 10710021 BANCO NACION - CTA DETRACCION | C14: 20517562158 | D14: CONSTRUCTORA & INMOBILIARIA SAGITARIO Y ASOCIADOS S.A.C. - SAGITARIO & ASOCIADOS S.A.C. | E14: 02. Transferencia a cuenta bancaria | F14: 0000001910 | G14: Caja y Bancos | H14: 46023 | I14: 202601 Enero 2026 | J14: 09/01/2026 | K14: FE E001-00000246 | L14: FE E001-00000246 | M14: S/ | N14: 2124 | O14: 2124 | P14: SERVICIO DE ACOMPANAMIENTO Y ASESORIA TECNICO-LEGAL EN EL PROYECTO: MEJORAMIENTO Y AMPLIACION DE LOS SERVICIOS DE SALUD DEL ESTABLECIMIENTO DE SALUD TUPAC AMARU,DISTRITO DE TUPAC AMARU,PROV PISCO,DEPARTAMENTO DE ICA. ACORDE CON ADENDA N° 01 AL CONTRATO N° 11-2024-TUPAC. | Q14: Transferencia a Cuenta Bancaria | R14: 2026 | S14: 15/12/2025
A15: a | B15: 10710021 BANCO NACION - CTA DETRACCION | C15: 20517562158 | D15: CONSTRUCTORA & INMOBILIARIA SAGITARIO Y ASOCIADOS S.A.C. - SAGITARIO & ASOCIADOS S.A.C. | E15: 02. Transferencia a cuenta bancaria | F15: 0000001871 | G15: Caja y Bancos | H15: 46023 | I15: 202601 Enero 2026 | J15: 09/01/2026 | K15: FE E001-00000196 | L15: FE E001-00000196 | M15: S/ | N15: 2124 | O15: 2124 | P15: SERVICIO DE ACOMPANAMIENTO Y ASESORIA TECNICO-LEGAL EN EL PROYECTO: MEJORAMIENTO Y AMPLIACION E LOS SERVICIOS DE SALUD DEL ESTABLECIMIENTO DE SALUD APOYO PALPA,DISTRITO DE PALPA, PROV DE PALPA,DEPARTAMENTO DE ICA. ACORDE CON ADENDA N° 01 AL CONTRATO N° 14-2024-PALPA. | Q15: Transferencia a Cuenta Bancaria | R15: 2026 | S15: 15/10/2025
A16: a | B16: 10710021 BANCO NACION - CTA DETRACCION | C16: 20517562158 | D16: CONSTRUCTORA & INMOBILIARIA SAGITARIO Y ASOCIADOS S.A.C. - SAGITARIO & ASOCIADOS S.A.C. | E16: 02. Transferencia a cuenta bancaria | F16: 0000001919 | G16: Caja y Bancos | H16: 46023 | I16: 202601 Enero 2026 | J16: 09/01/2026 | K16: FE E001-00000249 | L16: FE E001-00000249 | M16: S/ | N16: 2124 | O16: 2124 | P16: SERVICIO DE ACOMPANAMIENTO Y ASESORIA TECNICO-LEGAL EN EL PROYECTO: MEJORAMIENTO Y AMPLIACION E LOS SERVICIOS DE SALUD DEL ESTABLECIMIENTO DE SALUD APOYO PALPA,DISTRITO DE PALPA, PROV DE PALPA,DEPARTAMENTO DE ICA. ACORDE CON ADENDA N° 01 AL CONTRATO N° 14-2024-PALPA. | Q16: Transferencia a Cuenta Bancaria | R16: 2026 | S16: 15/12/2025
A17: a | B17: 10710021 BANCO NACION - CTA DETRACCION | C17: 20517562158 | D17: CONSTRUCTORA & INMOBILIARIA SAGITARIO Y ASOCIADOS S.A.C. - SAGITARIO & ASOCIADOS S.A.C. | E17: 02. Transferencia a cuenta bancaria | F17: 0000001877 | G17: Caja y Bancos | H17: 46023 | I17: 202601 Enero 2026 | J17: 09/01/2026 | K17: FE E001-00000198 | L17: FE E001-00000198 | M17: S/ | N17: 2124 | O17: 2124 | P17: SERVICIO DE ACOMPANAMIENTO Y ASESORIA TECNICO-LEGAL EN PROY: CONTRAT.DE LA EJECUCION DE LA OBRA:MEJORAMIENTO DE LA CAPACIDAD RESOLUTIVA DE LOS SERVICIOS DE SALUD DEL HOSPITAL DE FERREÑAFE,DIST. FERREÑAFE,PROV.FERREÑAFE,REGION LAMBAYEQUE.CUI 2310820. ACORDE AL CONTRATO DE PRESTACION DE SERVICIOS DE ASESORIA TECNICO-LEGAL N° 16- 2025-FERREÑAFE. | Q17: Transferencia a Cuenta Bancaria | R17: 2026 | S17: 15/10/2025
... A85: a | B85: 10410013 BBVA CONTINENTAL MN | C85: 20613390996 | D85: CONSORCIO HEALTH BERNALES | E85: 02. Transferencia a cuenta bancaria | F85: 0000001002 | G85: Caja y Bancos | H85: 46082 | I85: 202603 Marzo 2026 | J85: 01/03/2026 | K85: FE E001-00000315 | L85: FE E001-00000315 | M85: S/ | N85: 519200 | O85: 519200 | P85: SERVICIO DE ASESORIA INTEGRAL EN LA ADMINISTRACION CONTRACTUAL PARA EL PROCESO: DISEÑO CONSTRUCCION Y EQUIPAMIENTO DEL NUEVO HOSPITAL NACIONAL SERGIO BERNALES, LOCALIDAD DE COLLIQUE, DISTRITO DE COMAS, PROVINCIA DE LIMA - SEGUN ADENDA AL CONTRATO 003.2024/CH-1 // SERVICIO CORRESPONDIENTE AL MES DE ENERO 2026. | Q85: FECHA VALOR 28/02 EECC REFLEJADO EN MARZO | R85: 2026 | S85: 18/02/2026
A86: Total a | O86: =SUBTOTAL(9,O6:O85) -> 5560371.2
A87: b | B87: 10410014 BBVA CONTINENTAL ME | D87: YUPANQUI ARTADI, REYNALDO RICARDO | E87: 02. Transferencia a cuenta bancaria | F87: 0000002098 | G87: Caja y Bancos | H87: 46023 | I87: 202601 Enero 2026 | J87: 26/01/2026 | K87: PR 0000000607 | L87: PR 0000000607 | M87: U$ | N87: 45000 | O87: 151155 | P87: PRESTAMO DE REYNALDO A INTEGRAL | Q87: Transferencia a Cuenta Bancaria | R87: 2026 | S87: 26/01/2026
A88: b | B88: 10410014 BBVA CONTINENTAL ME | D88: YUPANQUI ARTADI, REYNALDO RICARDO | E88: 02. Transferencia a cuenta bancaria | F88: 0000002099 | G88: Caja y Bancos | H88: 46023 | I88: 202601 Enero 2026 | J88: 26/01/2026 | K88: PR 0000000608 | L88: PR 0000000608 | M88: U$ | N88: 45000 | O88: 151155 | P88: PRESTAMO DE REYNALDO A INTEGRAL | Q88: Transferencia a Cuenta Bancaria | R88: 2026 | S88: 26/01/2026
A89: b | B89: 10410013 BBVA CONTINENTAL MN | D89: YUPANQUI ARTADI, REYNALDO RICARDO | E89: 02. Transferencia a cuenta bancaria | F89: 0000002090 | G89: Caja y Bancos | H89: 46023 | I89: 202601 Enero 2026 | J89: 19/01/2026 | K89: PR 0000000589 | L89: PR 0000000589 | M89: S/ | N89: 105000 | O89: 105000 | P89: PRESTAMO DE RY ( ICYS) | Q89: PRESTAMO DE ICYS RY | R89: 2026 | S89: 19/01/2026
A90: b | B90: 10410014 BBVA CONTINENTAL ME | D90: YUPANQUI ARTADI, REYNALDO RICARDO | E90: 02. Transferencia a cuenta bancaria | F90: 0000000609 | G90: Caja y Bancos | H90: 46054 | I90: 202602 Febrero 2026 | J90: 07/02/2026 | K90: PR 0000000639 | L90: PR 0000000639 | M90: U$ | N90: 11850 | O90: 39851.55 | P90: PRESTAMO DE REYNALDO A INTEGRAL | Q90: PRESTAMO DE RY | R90: 2026 | S90: 07/02/2026
A91: b | B91: 10410013 BBVA CONTINENTAL MN | C91: 10415120911 | D91: GUTIERREZ ACQUARONE, GUSTAVO | E91: 02. Transferencia a cuenta bancaria | F91: 0000000605 | G91: Caja y Bancos | H91: 46054 | I91: 202602 Febrero 2026 | J91: 17/02/2026 | K91: DEV 0000000018 | L91: DEV 0000000018 | M91: S/ | N91: 204 | O91: 204 | P91: DEVOLUCION DE ER GG | Q91: DEVOLUCION DE ER | R91: 2026 | S91: 17/02/2026
A92: b | B92: 10410014 BBVA CONTINENTAL ME | E92: 14. Diferencia de cambio - Cuentas | F92: 0000000380 | G92: Diferencia de Cambio | H92: 46054 | I92: 202602 Febrero 2026 | J92: 28/02/2026 | M92: U$ | N92: 0 | O92: 439.12 | P92: Diferencia de cambio - Por Cuenta | Q92: Diferencia de cambio - Por Cuenta | R92: 2026 | S92: 28/02/2026
A93: b | B93: 10410013 BBVA CONTINENTAL MN | C93: 10074121395 | D93: JONES PATRONI, GUILLERMO AUGUSTO | E93: 02. Transferencia a cuenta bancaria | F93: 0000000876 | G93: Caja y Bancos | H93: 46082 | I93: 202603 Marzo 2026 | J93: 13/03/2026 | K93: DEV 0000000019 | L93: DEV 0000000019 | M93: S/ | N93: 3.12 | O93: 3.12 | P93: DEVOLUCION DE ER WILLY JONES | Q93: Transferencia a Cuenta Bancaria | R93: 2026 | S93: 13/03/2026
A94: b | B94: 10410014 BBVA CONTINENTAL ME | C94: 20536612972 | D94: CMO GROUP S.A. | E94: 02. Transferencia a cuenta bancaria | F94: 0000000822 | G94: Caja y Bancos | H94: 46082 | I94: 202603 Marzo 2026 | J94: 04/03/2026 | K94: DP 0000000030 | L94: DP 0000000030 | M94: U$ | N94: 95948 | O94: 326990.78 | P94: INGRESOS DE CMO SEGUN EECC (O.PAGO REC EXT LIQ:9675785) | Q94: INGRESOS CMO | R94: 2026 | S94: 04/03/2026
A95: b | B95: 10410014 BBVA CONTINENTAL ME | E95: 14. Diferencia de cambio - Cuentas | F95: 0000000485 | G95: Diferencia de Cambio | H95: 46082 | I95: 202603 Marzo 2026 | J95: 31/03/2026 | M95: U$ | N95: 0 | O95: 140.3 | P95: Diferencia de cambio - Por Cuenta | Q95: Diferencia de cambio - Por Cuenta | R95: 2026 | S95: 31/03/2026
A96: Total b | O96: =SUBTOTAL(9,O87:O95) -> 774938.87
A97: c | B97: 10410013 BBVA CONTINENTAL MN | C97: 10443226350 | D97: PACHECO CHUQUILIN, JEANETH CRISTY | E97: 03. Pago | F97: 0000000124 | G97: Libro Diario | H97: 46023 | I97: 202601 Enero 2026 | J97: 08/01/2026 | K97: RH E001-0000000009 | L97: RH E001-0000000009 | M97: S/ | N97: -1039.6 | O97: -1039.6 | P97: CAPACITACION EN SISTEMA ERP S10 POR LOS MESES DE NOVIEMBRE Y DICIEMBRE DEL 2025. | Q97: PAGO DE SERV. HONORARIOS JP | R97: 2026 | S97: 08/01/2026
A98: c | B98: 10410013 BBVA CONTINENTAL MN | C98: 15608157376 | D98: VELASQUEZ PEREZ, JUAN PABLO | E98: 03. Pago | F98: 0000000139 | G98: Libro Diario | H98: 46023 | I98: 202601 Enero 2026 | J98: 30/01/2026 | K98: RH E001-0000000033 | L98: RH E001-0000000033 | M98: S/ | N98: -6600 | O98: -6600 | P98: SERVICIO DE REVISION Y EDICION DE VIDEO EN TEMPORADA NAVIDEÑA 2025 | Q98: 30/01 PAGO DE SERV. HONORARIOS ENERO 2026 | R98: 2026 | S98: 30/01/2026
A99: c | B99: 10410014 BBVA CONTINENTAL ME | C99: 10103167154 | D99: INDACOCHEA CACEDA, FELIX ALEJANDRO | E99: 03. Pago | F99: 0000000146 | G99: Libro Diario | H99: 46023 | I99: 202601 Enero 2026 | J99: 30/01/2026 | K99: RH E001-0000000048 | L99: RH E001-0000000048 | M99: U$ | N99: -2760 | O99: -9232.2 | P99: ASESORIA DE ESTRUCTURACIÓN FINANCIERA - DICIEMBRE 2025 | Q99: PAGO DE SERV. DIETAS INDACOCHEA | R99: 2026 | S99: 30/01/2026
A100: c | B100: 10410013 BBVA CONTINENTAL MN | C100: 10460865528 | D100: MEDINA FLORES, JUAN CARLOS | E100: 03. Pago | F100: 0000000127 | G100: Libro Diario | H100: 46023 | I100: 202601 Enero 2026 | J100: 30/01/2026 | K100: RH E001-0000000109 | L100: RH E001-0000000109 | M100: S/ | N100: -26864 | O100: -26864 | P100: SERVICIO DE CONSULTORIA LEGAL ESPECIALIZADA EN GESTION CONTRACTUAL - ENERO 2026 | Q100: PAGO DE SERV. HONORARIOS JCM ENERO 2026 | R100: 2026 | S100: 30/01/2026
A101: c | B101: 10410013 BBVA CONTINENTAL MN | C101: 10094866249 | D101: MEDINA AIQUIPA, DAVID BERNABE | E101: 03. Pago | F101: 0000000130 | G101: Libro Diario | H101: 46023 | I101: 202601 Enero 2026 | J101: 30/01/2026 | K101: RH E001-0000000240 | L101: RH E001-0000000240 | M101: S/ | N101: -20000 | O101: -20000 | P101: SERVICIO DE ASESORIA EN GESTION CONTRACTUAL DE OBRAS PÚBLICAS MES DE ENERO 2026 | Q101: PAGO DE SERV. HONORARIOS DM Y AC ENERO 2026 | R101: 2026 | S101: 30/01/2026
A102: c | B102: 10410014 BBVA CONTINENTAL ME | C102: 10087738545 | D102: BARRIOS FERNANDEZ, CONCHA RAUL HERNANDO MARTIN | E102: 03. Pago | F102: 0000000143 | G102: Libro Diario | H102: 46023 | I102: 202601 Enero 2026 | J102: 30/01/2026 | K102: RH E001-0000000260 | L102: RH E001-0000000260 | M102: U$ | N102: -4600 | O102: -15387 | P102: DIETA DE DIRECTORIO | Q102: PAGO DE SERV. DIETAS BARRIOS | R102: 2026 | S102: 30/01/2026
A103: c | B103: 10410013 BBVA CONTINENTAL MN | C103: 20100130204 | D103: BANCO CONTINENTAL | E103: 03. Pago | F103: 0000002062 | G103: Libro Diario | H103: 46023 | I103: 202601 Enero 2026 | J103: 30/01/2026 | K103: RPR -0054951777 | L103: RPR 0054951777 | M103: S/ | N103: -1500 | O103: -1500 | P103: PLANILLA DE PAGO PRACTICANTES | Q103: 30/01 PLANILLA DE PRACTICANTES | R103: 2026 | S103: 30/01/2026
A104: c | B104: 10410013 BBVA CONTINENTAL MN | C104: 20100047218 | D104: BANCO DE CREDITO DEL PERU | E104: 03. Pago | F104: 0000002063 | G104: Libro Diario | H104: 46023 | I104: 202601 Enero 2026 | J104: 30/01/2026 | K104: RPR -0054951778 | L104: RPR 0054951778 | M104: S/ | N104: -1130 | O104: -1130 | P104: PLANILLA DE PAGO PRACTICANTES | Q104: 30/01 PLANILLA DE PRACTICANTES | R104: 2026 | S104: 30/01/2026
A105: c | B105: 10410013 BBVA CONTINENTAL MN | C105: 20100130204 | D105: BANCO CONTINENTAL | E105: 03. Pago | F105: 0000002087 | G105: Libro Diario | H105: 46023 | I105: 202601 Enero 2026 | J105: 30/01/2026 | K105: RPR 0054951783 | L105: RPR 0054951783 | M105: S/ | N105: -148170.82 | O105: -148170.82 | P105: PLANILLA DE PAGO EMPLEADOS | Q105: 30/01 PLANILLA ENERO EMPLEADOS | R105: 2026 | S105: 30/01/2026
A106: c | B106: 10410013 BBVA CONTINENTAL MN | C106: 20100130204 | D106: BANCO CONTINENTAL | E106: 03. Pago | F106: 0000002088 | G106: Libro Diario | H106: 46023 | I106: 202601 Enero 2026 | J106: 30/01/2026 | K106: RPR 0054951783 | L106: RPR 0054951783 | M106: S/ | N106: -7661.61 | O106: -7661.61 | P106: PLANILLA DE PAGO EMPLEADOS | Q106: 30/01 PLANILLA ENERO EMPLEADOS O/B | R106: 2026 | S106: 30/01/2026
A107: c | B107: 10410013 BBVA CONTINENTAL MN | C107: 20100053455 | D107: BANCO INTERNACIONAL DEL PERU - INTERBANK | E107: 03. Pago | F107: 0000002088 | G107: Libro Diario | H107: 46023 | I107: 202601 Enero 2026 | J107: 30/01/2026 | K107: RPR -0054951784 | L107: RPR 0054951784 | M107: S/ | N107: -8199.64 | O107: -8199.64 | P107: PLANILLA DE PAGO EMPLEADOS | Q107: 30/01 PLANILLA ENERO EMPLEADOS O/B | R107: 2026 | S107: 30/01/2026
A108: c | B108: 10410013 BBVA CONTINENTAL MN | C108: 20100043140 | D108: SCOTIABANK PERU S.A.A. | E108: 03. Pago | F108: 0000002088 | G108: Libro Diario | H108: 46023 | I108: 202601 Enero 2026 | J108: 30/01/2026 | K108: RPR -0054951785 | L108: RPR 0054951785 | M108: S/ | N108: -20009.49 | O108: -20009.49 | P108: PLANILLA DE PAGO EMPLEADOS | Q108: 30/01 PLANILLA ENERO EMPLEADOS O/B | R108: 2026 | S108: 30/01/2026
... A138: c | B138: 10410013 BBVA CONTINENTAL MN | C138: 10771013193 | D138: CCORISAPRA MUÑOZ, ALEXNIEL | E138: 03. Pago | F138: 0000000705 | G138: Libro Diario | H138: 46082 | I138: 202603 Marzo 2026 | J138: 30/03/2026 | K138: RH E001-0000000069 | L138: RH E001-0000000069 | M138: S/ | N138: -600 | O138: -600 | P138: SERVICIO DE APOYO EN TI - SISTEMAS MARZO 2026 | Q138: 30/03 PAGO HONORARIOS BBVA | R138: 2026 | S138: 30/03/2026
A139: Total c | O139: =SUBTOTAL(9,O97:O138) -> -835295.83
A140: d | B140: 10410013 BBVA CONTINENTAL MN | C140: 20100130204 | D140: BANCO CONTINENTAL | E140: 03. Pago | F140: 0000001963 | G140: Libro Diario | H140: 46023 | I140: 202601 Enero 2026 | J140: 30/01/2026 | K140: AP 0000000257 | L140: AP 0000000257 | M140: S/ | N140: -1 | O140: -1 | P140: COMISIONES BANCARIAS ENERO SOLES | Q140: PAGO DE COMISIONES MENSUALES ENERO 2026 | R140: 2026 | S140: 30/01/2026
A141: d | B141: 10410013 BBVA CONTINENTAL MN | C141: 20100130204 | D141: BANCO CONTINENTAL | E141: 03. Pago | F141: 0000001964 | G141: Libro Diario | H141: 46023 | I141: 202601 Enero 2026 | J141: 30/01/2026 | K141: AP 0000000257 | L141: AP 0000000257 | M141: S/ | N141: -1 | O141: -1 | P141: COMISIONES BANCARIAS ENERO SOLES | Q141: PAGO DE COMISIONES MENSUALES ENERO 2026 | R141: 2026 | S141: 30/01/2026
A142: d | B142: 10410013 BBVA CONTINENTAL MN | C142: 20100130204 | D142: BANCO CONTINENTAL | E142: 03. Pago | F142: 0000001943 | G142: Libro Diario | H142: 46023 | I142: 202601 Enero 2026 | J142: 08/01/2026 | K142: AP 0000000257 | L142: AP 0000000257 | M142: S/ | N142: -3.5 | O142: -3.5 | P142: COMISIONES BANCARIAS ENERO SOLES | Q142: PAGO DE COMISIONES MENSUALES ENERO 2026 | R142: 2026 | S142: 08/01/2026
A143: d | B143: 10410013 BBVA CONTINENTAL MN | C143: 20100130204 | D143: BANCO CONTINENTAL | E143: 03. Pago | F143: 0000001944 | G143: Libro Diario | H143: 46023 | I143: 202601 Enero 2026 | J143: 08/01/2026 | K143: AP 0000000257 | L143: AP 0000000257 | M143: S/ | N143: -3.5 | O143: -3.5 | P143: COMISIONES BANCARIAS ENERO SOLES | Q143: PAGO DE COMISIONES MENSUALES ENERO 2026 | R143: 2026 | S143: 08/01/2026
A144: d | B144: 10410013 BBVA CONTINENTAL MN | C144: 20100130204 | D144: BANCO CONTINENTAL | E144: 03. Pago | F144: 0000001945 | G144: Libro Diario | H144: 46023 | I144: 202601 Enero 2026 | J144: 08/01/2026 | K144: AP 0000000257 | L144: AP 0000000257 | M144: S/ | N144: -3.5 | O144: -3.5 | P144: COMISIONES BANCARIAS ENERO SOLES | Q144: PAGO DE COMISIONES MENSUALES ENERO 2026 | R144: 2026 | S144: 08/01/2026
A145: d | B145: 10410013 BBVA CONTINENTAL MN | C145: 20100130204 | D145: BANCO CONTINENTAL | E145: 03. Pago | F145: 0000001946 | G145: Libro Diario | H145: 46023 | I145: 202601 Enero 2026 | J145: 08/01/2026 | K145: AP 0000000257 | L145: AP 0000000257 | M145: S/ | N145: -3.5 | O145: -3.5 | P145: COMISIONES BANCARIAS ENERO SOLES | Q145: PAGO DE COMISIONES MENSUALES ENERO 2026 | R145: 2026 | S145: 08/01/2026
A146: d | B146: 10410013 BBVA CONTINENTAL MN | C146: 20100130204 | D146: BANCO CONTINENTAL | E146: 03. Pago | F146: 0000001947 | G146: Libro Diario | H146: 46023 | I146: 202601 Enero 2026 | J146: 08/01/2026 | K146: AP 0000000257 | L146: AP 0000000257 | M146: S/ | N146: -3.5 | O146: -3.5 | P146: COMISIONES BANCARIAS ENERO SOLES | Q146: PAGO DE COMISIONES MENSUALES ENERO 2026 | R146: 2026 | S146: 08/01/2026
A147: d | B147: 10410013 BBVA CONTINENTAL MN | C147: 20100130204 | D147: BANCO CONTINENTAL | E147: 03. Pago | F147: 0000001948 | G147: Libro Diario | H147: 46023 | I147: 202601 Enero 2026 | J147: 08/01/2026 | K147: AP 0000000257 | L147: AP 0000000257 | M147: S/ | N147: -3.5 | O147: -3.5 | P147: COMISIONES BANCARIAS ENERO SOLES | Q147: PAGO DE COMISIONES MENSUALES ENERO 2026 | R147: 2026 | S147: 08/01/2026
A148: d | B148: 10410013 BBVA CONTINENTAL MN | C148: 20100130204 | D148: BANCO CONTINENTAL | E148: 03. Pago | F148: 0000001949 | G148: Libro Diario | H148: 46023 | I148: 202601 Enero 2026 | J148: 08/01/2026 | K148: AP 0000000257 | L148: AP 0000000257 | M148: S/ | N148: -3.5 | O148: -3.5 | P148: COMISIONES BANCARIAS ENERO SOLES | Q148: PAGO DE COMISIONES MENSUALES ENERO 2026 | R148: 2026 | S148: 08/01/2026
A149: d | B149: 10410013 BBVA CONTINENTAL MN | C149: 20100130204 | D149: BANCO CONTINENTAL | E149: 03. Pago | F149: 0000001950 | G149: Libro Diario | H149: 46023 | I149: 202601 Enero 2026 | J149: 08/01/2026 | K149: AP 0000000257 | L149: AP 0000000257 | M149: S/ | N149: -3.5 | O149: -3.5 | P149: COMISIONES BANCARIAS ENERO SOLES | Q149: PAGO DE COMISIONES MENSUALES ENERO 2026 | R149: 2026 | S149: 08/01/2026
A150: d | B150: 10410013 BBVA CONTINENTAL MN | C150: 20100130204 | D150: BANCO CONTINENTAL | E150: 03. Pago | F150: 0000001951 | G150: Libro Diario | H150: 46023 | I150: 202601 Enero 2026 | J150: 08/01/2026 | K150: AP 0000000257 | L150: AP 0000000257 | M150: S/ | N150: -3.5 | O150: -3.5 | P150: COMISIONES BANCARIAS ENERO SOLES | Q150: PAGO DE COMISIONES MENSUALES ENERO 2026 | R150: 2026 | S150: 08/01/2026
A151: d | B151: 10410013 BBVA CONTINENTAL MN | C151: 20100130204 | D151: BANCO CONTINENTAL | E151: 03. Pago | F151: 0000001952 | G151: Libro Diario | H151: 46023 | I151: 202601 Enero 2026 | J151: 08/01/2026 | K151: AP 0000000257 | L151: AP 0000000257 | M151: S/ | N151: -3.5 | O151: -3.5 | P151: COMISIONES BANCARIAS ENERO SOLES | Q151: PAGO DE COMISIONES MENSUALES ENERO 2026 | R151: 2026 | S151: 08/01/2026
... A187: d | B187: 10410014 BBVA CONTINENTAL ME | C187: 20100130204 | D187: BANCO CONTINENTAL | E187: 03. Pago | F187: 0000002126 | G187: Libro Diario | H187: 46023 | I187: 202601 Enero 2026 | J187: 30/01/2026 | K187: DP 0000000952 | L187: DP 0000000952 | M187: U$ | N187: -11.35 | O187: -37.97 | P187: ITF ENERO DOLARES | Q187: 01/01 COMISIONES BANCARIAS DE ENERO | R187: 2026 | S187: 30/01/2026
A188: d | B188: 10410014 BBVA CONTINENTAL ME | D188: CORNEJO DAVILA, VANINNA JUISA | E188: 03. Pago | F188: 0000002106 | G188: Libro Diario | H188: 46023 | I188: 202601 Enero 2026 | J188: 26/01/2026 | K188: PR 0000000602 | L188: PR 0000000602 | M188: U$ | N188: -90000 | O188: -302310 | P188: PRESTAMO A VC | Q188: 26/01 PRESTAMO A VC | R188: 2026 | S188: 26/01/2026
A189: d | B189: 10410013 BBVA CONTINENTAL MN | D189: YUPANQUI ARTADI, REYNALDO RICARDO | E189: 03. Pago | F189: 0000002003 | G189: Libro Diario | H189: 46023 | I189: 202601 Enero 2026 | J189: 14/01/2026 | K189: PR 0000000588 | L189: PR 0000000588 | M189: S/ | N189: -210000 | O189: -210000 | P189: PRESTAMO A RYA - CALIDAD Y GESTION | Q189: 14/01 PRESTAMO CALIDAD Y GESTION RY | R189: 2026 | S189: 14/01/2026
A190: d | B190: 10410013 BBVA CONTINENTAL MN | C190: 20601546478 | D190: PANORAMICA TECHNOLOGY S.A.C. | E190: 03. Pago | F190: 0000002049 | G190: Libro Diario | H190: 46023 | I190: 202601 Enero 2026 | J190: 30/01/2026 | K190: AP 0000000261 | L190: AP 0000000261 | M190: S/ | N190: -78735.9 | O190: -78735.9 | P190: ADELANTO PARA CULMINACION DE TRABAJO DE SISTEMA DE COMUNICACIONES | Q190: 30/01 PAGO A PROVEEDORES | R190: 2026 | S190: 30/01/2026
A191: d | B191: 10410014 BBVA CONTINENTAL ME | C191: 20536612972 | D191: CMO GROUP S.A. | E191: 03. Pago | F191: 0000002115 | G191: Libro Diario | H191: 46023 | I191: 202601 Enero 2026 | J191: 30/01/2026 | K191: PR 0000000605 | L191: PR 0000000605 | M191: U$ | N191: -15000 | O191: -50175 | P191: PRESTAMO A CMO // ANCONA | Q191: 30/01 PRESTAMO A CMO: ANCONA | R191: 2026 | S191: 30/01/2026
A192: d | B192: 10410013 BBVA CONTINENTAL MN | C192: 10097521889 | D192: GOMERO ROJAS, GUILLERMO ALBERTO | E192: 03. Pago | F192: 0000002086 | G192: Libro Diario | H192: 46023 | I192: 202601 Enero 2026 | J192: 13/01/2026 | K192: PR 0000000600 | L192: PR 0000000600 | M192: S/ | N192: -45000 | O192: -45000 | P192: PRESTAMO A GG - SERV. GENERALES C&C | Q192: 13/01 PRESTAMO A GG - SERV. GENERALES | R192: 2026 | S192: 13/01/2026
A193: d | B193: 10410014 BBVA CONTINENTAL ME | C193: 20536612972 | D193: CMO GROUP S.A. | E193: 03. Pago | F193: 0000002113 | G193: Libro Diario | H193: 46023 | I193: 202601 Enero 2026 | J193: 30/01/2026 | K193: PR 0000000603 | L193: PR 0000000603 | M193: U$ | N193: -11800 | O193: -39471 | P193: PRESTAMO A CMO // ESTUDIO CARO F002-434 | Q193: 30/01 PRESTAMO A CMO: ESTUDIO CARO | R193: 2026 | S193: 30/01/2026
A194: d | B194: 10410013 BBVA CONTINENTAL MN | C194: 20536612972 | D194: CMO GROUP S.A. | E194: 03. Pago | F194: 0000002020 | G194: Libro Diario | H194: 46023 | I194: 202601 Enero 2026 | J194: 30/01/2026 | K194: PR 0000000590 | L194: PR 0000000590 | M194: S/ | N194: -27652.11 | O194: -27652.11 | P194: PRESTAMO A CMO: PLANILLA ENERO | Q194: 30/01 PRESTAMO A CMO: PLANILLA ENERO 26 | R194: 2026 | S194: 30/01/2026
A195: d | B195: 10410013 BBVA CONTINENTAL MN | C195: 20536612972 | D195: CMO GROUP S.A. | E195: 03. Pago | F195: 0000002078 | G195: Libro Diario | H195: 46023 | I195: 202601 Enero 2026 | J195: 30/01/2026 | K195: PR 0000000596 | L195: PR 0000000596 | M195: S/ | N195: -25000 | O195: -25000 | P195: PRESTAMO A CMO POR PAGO A PROVEEDORES - LBS | Q195: 30/01 PRESTAMO A CMO: PAGO A PROVEEDORES | R195: 2026 | S195: 30/01/2026
A196: d | B196: 10410013 BBVA CONTINENTAL MN | C196: 20536612972 | D196: CMO GROUP S.A. | E196: 03. Pago | F196: 0000002016 | G196: Libro Diario | H196: 46023 | I196: 202601 Enero 2026 | J196: 20/01/2026 | K196: PR 0000000595 | L196: PR 0000000595 | M196: S/ | N196: -20000 | O196: -20000 | P196: PRESTAMO A CMO // IMPUESTOS | Q196: 20/01 PRESTAMO A CMO: IMPUESTOS | R196: 2026 | S196: 20/01/2026
A197: d | B197: 10410013 BBVA CONTINENTAL MN | C197: 20536612972 | D197: CMO GROUP S.A. | E197: 03. Pago | F197: 0000002070 | G197: Libro Diario | H197: 46023 | I197: 202601 Enero 2026 | J197: 30/01/2026 | K197: PR 0000000596 | L197: PR 0000000596 | M197: S/ | N197: -20000 | O197: -20000 | P197: PRESTAMO A CMO POR PAGO A PROVEEDORES - LBS | Q197: 30/01 PRESTAMO A CMO: PAGO A PROVEEDORES | R197: 2026 | S197: 30/01/2026
A198: d | B198: 10410013 BBVA CONTINENTAL MN | C198: 20536612972 | D198: CMO GROUP S.A. | E198: 03. Pago | F198: 0000002071 | G198: Libro Diario | H198: 46023 | I198: 202601 Enero 2026 | J198: 30/01/2026 | K198: PR 0000000596 | L198: PR 0000000596 | M198: S/ | N198: -20000 | O198: -20000 | P198: PRESTAMO A CMO POR PAGO A PROVEEDORES - LBS | Q198: 30/01 PRESTAMO A CMO: PAGO A PROVEEDORES | R198: 2026 | S198: 30/01/2026
A199: d | B199: 10410013 BBVA CONTINENTAL MN | C199: 20536612972 | D199: CMO GROUP S.A. | E199: 03. Pago | F199: 0000002079 | G199: Libro Diario | H199: 46023 | I199: 202601 Enero 2026 | J199: 30/01/2026 | K199: PR 0000000596 | L199: PR 0000000596 | M199: S/ | N199: -20000 | O199: -20000 | P199: PRESTAMO A CMO POR PAGO A PROVEEDORES - LBS | Q199: 30/01 PRESTAMO A CMO: PAGO A PROVEEDORES | R199: 2026 | S199: 30/01/2026
A200: d | B200: 10410013 BBVA CONTINENTAL MN | C200: 20431115825 | D200: PACIFICO SA ENT PRESTADORA DE SALUD | E200: 03. Pago | F200: 0000002043 | G200: Libro Diario | H200: 46023 | I200: 202601 Enero 2026 | J200: 30/01/2026 | K200: F F027-01053589 | L200: F F027-01053589 | M200: S/ | N200: -18563.68 | O200: -18563.68 | P200: SEGURO EPS // A/COB 9985023 // DOC R-4344398 // VIGENCIA 01/01/2026 AL 31/01/2026 | Q200: 30/01 PAGO A PROVEEDORES | R200: 2026 | S200: 30/01/2026
A201: d | B201: 10410013 BBVA CONTINENTAL MN | C201: 20536612972 | D201: CMO GROUP S.A. | E201: 03. Pago | F201: 0000002074 | G201: Libro Diario | H201: 46023 | I201: 202601 Enero 2026 | J201: 30/01/2026 | K201: PR 0000000596 | L201: PR 0000000596 | M201: S/ | N201: -16875 | O201: -16875 | P201: PRESTAMO A CMO POR PAGO A PROVEEDORES - LBS | Q201: 30/01 PRESTAMO A CMO: PAGO A PROVEEDORES | R201: 2026 | S201: 30/01/2026
... A262: d | B262: 10410013 BBVA CONTINENTAL MN | C262: 10088768197 | D262: BALAREZO ELIAS DE TIRADO, ANA GABRIELA | E262: 03. Pago | F262: 0000002004 | G262: Libro Diario | H262: 46023 | I262: 202601 Enero 2026 | J262: 19/01/2026 | K262: R 0000000001 | L262: R 0000000001 | M262: S/ | N262: -624.33 | O262: -624.33 | P262: CAJA CHICA - INTEGRAL // SEGUN CORREO 19.09.24 | Q262: 19/01 REEMBOLSO CAJA CHICA | R262: 2026 | S262: 19/01/2026
A263: d | B263: 10410013 BBVA CONTINENTAL MN | C263: 10000620471 | D263: VELASQUEZ URREGO, JUAN CARLOS | E263: 03. Pago | F263: 0000002051 | G263: Libro Diario | H263: 46023 | I263: 202601 Enero 2026 | J263: 30/01/2026 | M263: S/ | N263: -611.79 | O263: -611.79 | P263: 30/01 REEMBOLSO A COLABORADORES | Q263: 30/01 REEMBOLSO A COLABORADORES | R263: 2026 | S263: 30/01/2026
A264: d | B264: 10410013 BBVA CONTINENTAL MN | C264: 10771013193 | D264: CCORISAPRA MUÑOZ, ALEXNIEL | E264: 03. Pago | F264: 0000000130 | G264: Libro Diario | H264: 46023 | I264: 202601 Enero 2026 | J264: 30/01/2026 | K264: AP 0000000240 | L264: AP 0000000240 | M264: S/ | N264: -600 | O264: -600 | P264: ADELANTO POR SERVICIO ENERO 2026 | Q264: PAGO DE SERV. HONORARIOS DM Y AC ENERO 2026 | R264: 2026 | S264: 30/01/2026
A265: d | B265: 10410013 BBVA CONTINENTAL MN | C265: 10088768197 | D265: BALAREZO ELIAS DE TIRADO, ANA GABRIELA | E265: 03. Pago | F265: 0000002146 | G265: Libro Diario | H265: 46023 | I265: 202601 Enero 2026 | J265: 30/01/2026 | K265: R 0000000001 | L265: R 0000000001 | M265: S/ | N265: -581.9 | O265: -581.9 | P265: CAJA CHICA - INTEGRAL // SEGUN CORREO 19.09.24 | Q265: 30/01 REEMBOLSO DE CAJA CHICA | R265: 2026 | S265: 30/01/2026
A266: d | B266: 10410013 BBVA CONTINENTAL MN | C266: 20418896915 | D266: MAPFRE PERU COMPAÑIA DE SEGUROS Y REASEGUROS | E266: 03. Pago | F266: 0000002039 | G266: Libro Diario | H266: 46023 | I266: 202601 Enero 2026 | J266: 30/01/2026 | K266: F F050-00749220 | L266: F F050-00749220 | M266: S/ | N266: -580.04 | O266: -580.04 | P266: SEGURO SCTR PENSIONES VALIDO DE 01/01/2026 AL 31/01/2026 - CT CANCELACION RECIBO 167389355 | Q266: 30/01 PAGO A PROVEEDORES | R266: 2026 | S266: 30/01/2026
A267: d | B267: 10410013 BBVA CONTINENTAL MN | C267: 20536612972 | D267: CMO GROUP S.A. | E267: 03. Pago | F267: 0000002065 | G267: Libro Diario | H267: 46023 | I267: 202601 Enero 2026 | J267: 30/01/2026 | K267: PR 0000000596 | L267: PR 0000000596 | M267: S/ | N267: -457.21 | O267: -457.21 | P267: PRESTAMO A CMO POR PAGO A PROVEEDORES - LBS | Q267: 30/01 PRESTAMO A CMO: PAGO A PROVEEDORES | R267: 2026 | S267: 30/01/2026
A268: d | B268: 10410013 BBVA CONTINENTAL MN | C268: 10422397596 | D268: TALLEDO GILVONIO MANUEL OMAR | E268: 03. Pago | F268: 0000000039 | G268: Libro Diario | H268: 46023 | I268: 202601 Enero 2026 | J268: 08/01/2026 | K268: F E001-00000018 | L268: F E001-00000018 | M268: S/ | N268: -447 | O268: -447 | P268: ADMINISTRACION DE REDES SOCIALES - SEPTIEMBRE - OCTUBRE 2025 + DISEÑO DE BROCHURE CORPORATIVO | Q268: PAGO DE DETRACCION TALLEDO E001-18 | R268: 2026 | S268: 08/01/2026
A269: d | B269: 10410014 BBVA CONTINENTAL ME | C269: 20100130204 | D269: BANCO CONTINENTAL | E269: 03. Pago | F269: 0000002118 | G269: Libro Diario | H269: 46023 | I269: 202601 Enero 2026 | J269: 26/01/2026 | K269: AP 0000000263 | L269: AP 0000000263 | M269: U$ | N269: -123.5 | O269: -414.84 | P269: COMISIONES BBVA DOLARES | Q269: 26/01 COMISIONES BANCARIAS DE ENERO | R269: 2026 | S269: 26/01/2026
A270: d | B270: 10410013 BBVA CONTINENTAL MN | C270: 10097521889 | D270: GOMERO ROJAS, GUILLERMO ALBERTO | E270: 03. Pago | F270: 0000002027 | G270: Libro Diario | H270: 46023 | I270: 202601 Enero 2026 | J270: 20/01/2026 | K270: PR 0000000599 | L270: PR 0000000599 | M270: S/ | N270: -413.51 | O270: -413.51 | P270: PRESTAMO A GG - LUMINARIAS | Q270: 20/01 PRESTAMO A GG - LUMINARIAS | R270: 2026 | S270: 20/01/2026
A271: d | B271: 10410013 BBVA CONTINENTAL MN | C271: 20536612972 | D271: CMO GROUP S.A. | E271: 03. Pago | F271: 0000002066 | G271: Libro Diario | H271: 46023 | I271: 202601 Enero 2026 | J271: 30/01/2026 | K271: PR 0000000596 | L271: PR 0000000596 | M271: S/ | N271: -387.7 | O271: -387.7 | P271: PRESTAMO A CMO POR PAGO A PROVEEDORES - LBS | Q271: 30/01 PRESTAMO A CMO: PAGO A PROVEEDORES | R271: 2026 | S271: 30/01/2026
A272: d | B272: 10410013 BBVA CONTINENTAL MN | C272: 20536612972 | D272: CMO GROUP S.A. | E272: 03. Pago | F272: 0000002069 | G272: Libro Diario | H272: 46023 | I272: 202601 Enero 2026 | J272: 30/01/2026 | K272: PR 0000000596 | L272: PR 0000000596 | M272: S/ | N272: -387.7 | O272: -387.7 | P272: PRESTAMO A CMO POR PAGO A PROVEEDORES - LBS | Q272: 30/01 PRESTAMO A CMO: PAGO A PROVEEDORES | R272: 2026 | S272: 30/01/2026
A273: d | B273: 10410013 BBVA CONTINENTAL MN | C273: 20107167481 | D273: FOTO PLUS S.R.L. | E273: 03. Pago | F273: 0000002050 | G273: Libro Diario | H273: 46023 | I273: 202601 Enero 2026 | J273: 30/01/2026 | K273: AP 0000000262 | L273: AP 0000000262 | M273: S/ | N273: -380 | O273: -380 | P273: ADELANTO A PROVEEDOR SEGUN EECC | Q273: 30/01 PAGO A PROVEEDORES | R273: 2026 | S273: 30/01/2026
A274: d | B274: 10410013 BBVA CONTINENTAL MN | C274: 20431115825 | D274: PACIFICO SA ENT PRESTADORA DE SALUD | E274: 03. Pago | F274: 0000002041 | G274: Libro Diario | H274: 46023 | I274: 202601 Enero 2026 | J274: 30/01/2026 | K274: ND FD12-00200362 | L274: ND FD12-00200362 | M274: S/ | N274: -376.87 | O274: -376.87 | P274: SEGURO PACIFICO EPS- SALUD// POLIZA: 128583 // VIG 01/11/2025 AL 30/11/2025 REF: F027-01035425 DEL 07.11.25 | Q274: 30/01 PAGO A PROVEEDORES | R274: 2026 | S274: 30/01/2026
A275: d | B275: 10410013 BBVA CONTINENTAL MN | C275: 10422397596 | D275: TALLEDO GILVONIO MANUEL OMAR | E275: 03. Pago | F275: 0000000037 | G275: Libro Diario | H275: 46023 | I275: 202601 Enero 2026 | J275: 08/01/2026 | K275: F E001-00000017 | L275: F E001-00000017 | M275: S/ | N275: -305 | O275: -305 | P275: ADMINISTRACION DE REDES SOCIALES - AGOSTO - SEPTIEMBRE 2025 | Q275: PAGO DE DETRACCION TALLEDO E001-17 | R275: 2026 | S275: 08/01/2026
... A279: d | B279: 10410014 BBVA CONTINENTAL ME | C279: 20257094465 | D279: AGENCIA DE ADUANA MACROMAR S.A. | E279: 03. Pago | F279: 0000002104 | G279: Libro Diario | H279: 46023 | I279: 202601 Enero 2026 | J279: 02/01/2026 | K279: AP 0000000264 | L279: AP 0000000264 | M279: U$ | N279: -64.9 | O279: -218.58 | P279: ADELANTO - MACROMAR AGENCIA DE ADUANAS - IMPORTACION DE ESCULTURA | Q279: 02/01 ADELANTO POR TRANSPORTE DE ESCULTURA | R279: 2026 | S279: 02/01/2026
A280: d | B280: 10410013 BBVA CONTINENTAL MN | D280: YUPANQUI ARTADI, REYNALDO RICARDO | E280: 03. Pago | F280: 0000002053 | G280: Libro Diario | H280: 46023 | I280: 202601 Enero 2026 | J280: 30/01/2026 | M280: S/ | N280: -195.8 | O280: -195.8 | P280: 30/01 REEMBOLSO A COLABORADORES | Q280: 30/01 REEMBOLSO A COLABORADORES | R280: 2026 | S280: 30/01/2026
A281: d | B281: 10410013 BBVA CONTINENTAL MN | C281: 20605246240 | D281: NEXUS CARGO S.A.C. | E281: 03. Pago | F281: 0000002033 | G281: Libro Diario | H281: 46023 | I281: 202601 Enero 2026 | J281: 30/01/2026 | K281: F E001-00002340 | L281: F E001-00002340 | M281: S/ | N281: -188.8 | O281: -188.8 | P281: SERVICIO DE TRASLADO DE CUADRO EN VAN EL 29 DE ENERO 2026-DESDE OFICINA MANUEL OLGUIN HACIA CERROS DE CAMACHO. | Q281: 30/01 PAGO A PROVEEDORES | R281: 2026 | S281: 30/01/2026
A282: d | B282: 10410013 BBVA CONTINENTAL MN | C282: 20536612972 | D282: CMO GROUP S.A. | E282: 03. Pago | F282: 0000002068 | G282: Libro Diario | H282: 46023 | I282: 202601 Enero 2026 | J282: 30/01/2026 | K282: PR 0000000596 | L282: PR 0000000596 | M282: S/ | N282: -188.23 | O282: -188.23 | P282: PRESTAMO A CMO POR PAGO A PROVEEDORES - LBS | Q282: 30/01 PRESTAMO A CMO: PAGO A PROVEEDORES | R282: 2026 | S282: 30/01/2026
A283: d | B283: 10410013 BBVA CONTINENTAL MN | C283: 20100130204 | D283: BANCO CONTINENTAL | E283: 03. Pago | F283: 0000002089 | G283: Libro Diario | H283: 46023 | I283: 202601 Enero 2026 | J283: 30/01/2026 | K283: DP 0000000889 | L283: DP 0000000889 | M283: S/ | N283: -152.7 | O283: -152.7 | P283: ITF + COMISION ENERO SOLES | Q283: 30/01 GASTOS BANCARIOS - ITF | R283: 2026 | S283: 30/01/2026
A284: d | B284: 10410013 BBVA CONTINENTAL MN | C284: 20609325543 | D284: VPX CLUB 108 S.A.C. | E284: 03. Pago | F284: 0000000056 | G284: Libro Diario | H284: 46023 | I284: 202601 Enero 2026 | J284: 08/01/2026 | K284: F FCL1-00001839 | L284: F FCL1-00001839 | M284: S/ | N284: -147 | O284: -147 | P284: GASTOS DIVERSOS - EVENTO DE FIN DE AÑO 2025 (18% ATENCION AL PERSONAL Y 82% PUBLICIDAD) | Q284: PAGO DE DETRACCION FCL1-1839 | R284: 2026 | S284: 08/01/2026
A285: d | B285: 10410013 BBVA CONTINENTAL MN | C285: 20332970411 | D285: PACIFICO COMPAÑIA DE SEGUROS Y REASEGUROS | E285: 03. Pago | F285: 0000002037 | G285: Libro Diario | H285: 46023 | I285: 202601 Enero 2026 | J285: 30/01/2026 | K285: F F091-00103013 | L285: F F091-00103013 | M285: S/ | N285: -119.98 | O285: -119.98 | P285: SEGURO FOLA // DOC AC 93826460 // POLIZA 21474364 // VIGENCIA 01/01/2026 AL 31/01/2026. | Q285: 30/01 PAGO A PROVEEDORES | R285: 2026 | S285: 30/01/2026
A286: d | B286: 10410013 BBVA CONTINENTAL MN | C286: 20600964608 | D286: SERVICIOS GENERALES DE CONSTRUCCION C & C S.A.C. | E286: 03. Pago | F286: 0000000033 | G286: Libro Diario | H286: 46023 | I286: 202601 Enero 2026 | J286: 08/01/2026 | K286: F E001-00000282 | L286: F E001-00000282 | M286: S/ | N286: -78 | O286: -78 | P286: CAMBIO DE REPUESTO DE MANIJA, VASTAGO Y EMBOLO DE FLUXOMETRO DE BAÑO DE VARONES. | Q286: PAGO DE DETRACCIONES | R286: 2026 | S286: 08/01/2026
A287: d | B287: 10410013 BBVA CONTINENTAL MN | D287: QUINO DUEÑAS, KIMBERLY JHOANA | E287: 03. Pago | F287: 0000002055 | G287: Libro Diario | H287: 46023 | I287: 202601 Enero 2026 | J287: 30/01/2026 | M287: S/ | N287: -68.2 | O287: -68.2 | P287: 30/01 REEMBOLSO A COLABORADORES | Q287: 30/01 REEMBOLSO A COLABORADORES | R287: 2026 | S287: 30/01/2026
A288: d | B288: 10410013 BBVA CONTINENTAL MN | D288: VILLEGAS TINEO, NICOLASA | E288: 03. Pago | F288: 0000002058 | G288: Libro Diario | H288: 46023 | I288: 202601 Enero 2026 | J288: 30/01/2026 | K288: DP 0000000901 | L288: DP 0000000901 | M288: S/ | N288: -49 | O288: -49 | P288: RECOJO DE LUMINARIAS | Q288: 30/01 REEMBOLSO A COLABORADORES | R288: 2026 | S288: 30/01/2026
A289: d | B289: 10410013 BBVA CONTINENTAL MN | C289: 10755406576 | D289: VERA OCAS, ALEXANDRA MARIBEL | E289: 03. Pago | F289: 0000002047 | G289: Libro Diario | H289: 46023 | I289: 202601 Enero 2026 | J289: 30/01/2026 | K289: DP 0000000902 | L289: DP 0000000902 | M289: S/ | N289: -45 | O289: -45 | P289: MOVILIDAD DESDE OFICINA - NOTARIA (RECOJO DE ESCRITO LEGALIZADO) // NOTARIA - SUNAT (PRESENTACION DE ESCRITO) // OFICINA - NOTARIA TELLO (LEGALIZACION DE LIBROS CONTABLES) // NOTARIA TELLO - MANUEL OLGUIN (RETORNO A LA OFICINA) | Q289: 30/01 PAGO A PROVEEDORES | R289: 2026 | S289: 30/01/2026
A290: d | B290: 10410013 BBVA CONTINENTAL MN | C290: 10755406576 | D290: VERA OCAS, ALEXANDRA MARIBEL | E290: 03. Pago | F290: 0000002047 | G290: Libro Diario | H290: 46023 | I290: 202601 Enero 2026 | J290: 30/01/2026 | K290: DP 0000000903 | L290: DP 0000000903 | M290: S/ | N290: -45 | O290: -45 | P290: MOVILIDAD DESDE OFICINA - BBVA SANTA CRUZ MIRAFLORES (DOCUMENTOS ACTUALIZADOS) // SANTA CRUZ 695 - SANTA CRUZ 381 (COPIA DE TESTIMONIO - ESCRITURA PUBLICA) // SANTA CRUZ MIRAFLORES - OFICINA SURCO (RETORNO A LA OFICINA) | Q290: 30/01 PAGO A PROVEEDORES | R290: 2026 | S290: 30/01/2026
A291: d | B291: 10410013 BBVA CONTINENTAL MN | C291: 10755406576 | D291: VERA OCAS, ALEXANDRA MARIBEL | E291: 03. Pago | F291: 0000002047 | G291: Libro Diario | H291: 46023 | I291: 202601 Enero 2026 | J291: 30/01/2026 | K291: DP 0000000904 | L291: DP 0000000904 | M291: S/ | N291: -45 | O291: -45 | P291: MOVILIDAD DESDE OFICINA OLGUIN - LAS AZUCENAS SURCO (DOCUMENTACION DE INTEGRAL EN ALMACEN) // LAS AZUCENAS SURCO - OFICINA SURCO (RETORNO A LA OFICINA CON DOCUMENTOS DE INTEGRAL). | Q291: 30/01 PAGO A PROVEEDORES | R291: 2026 | S291: 30/01/2026
A292: d | B292: 10410013 BBVA CONTINENTAL MN | C292: 10755406576 | D292: VERA OCAS, ALEXANDRA MARIBEL | E292: 03. Pago | F292: 0000002047 | G292: Libro Diario | H292: 46023 | I292: 202601 Enero 2026 | J292: 30/01/2026 | K292: DP 0000000905 | L292: DP 0000000905 | M292: S/ | N292: -45 | O292: -45 | P292: MOVILIDAD DESDE OFICINA SURCO - SUNAT SAN ISIDRO (PRESENTACION DE DOCUMENTOS SUNAT) // SUNAT SAN ISIDRO - OFICINA SURCO (RETORNO A LA OFICINA) | Q292: 30/01 PAGO A PROVEEDORES | R292: 2026 | S292: 30/01/2026
A293: d | B293: 10410013 BBVA CONTINENTAL MN | C293: 10755406576 | D293: VERA OCAS, ALEXANDRA MARIBEL | E293: 03. Pago | F293: 0000002047 | G293: Libro Diario | H293: 46023 | I293: 202601 Enero 2026 | J293: 30/01/2026 | K293: DP 0000000906 | L293: DP 0000000906 | M293: S/ | N293: -45 | O293: -45 | P293: MOVILIDAD DESDE SURCO - AV. EL DERBY (ENTREGA DE DOCUMENTOS EN EL DERBY) // SURCO - OFICINA (IMPRESIONES OFICINAS MANUEL OLGUIN) // EL DERBY - NOTARIA PEREZ TELLO (LEGALIZACION DE FIRMA) // NOTARIA PEREZ TELLO - OFICINA SURCO (RETORNO A LA OFICINA) | Q293: 30/01 PAGO A PROVEEDORES | R293: 2026 | S293: 30/01/2026
A294: d | B294: 10410013 BBVA CONTINENTAL MN | C294: 10755406576 | D294: VERA OCAS, ALEXANDRA MARIBEL | E294: 03. Pago | F294: 0000002047 | G294: Libro Diario | H294: 46023 | I294: 202601 Enero 2026 | J294: 30/01/2026 | K294: DP 0000000907 | L294: DP 0000000907 | M294: S/ | N294: -45 | O294: -45 | P294: MOVILIDAD DESDE OFICINA SURCO - SAN ISIDRO (FIRMAR FORMULARIOS CON EL DR. RAMIREZ) // SAN ISIDRO (LLEVAR FORMULARIOS A CRBC) // SAN ISIDRO - OFICINA SURCO (RETORNO A LA OFICINA) | Q294: 30/01 PAGO A PROVEEDORES | R294: 2026 | S294: 30/01/2026
...

Sheet Detalle S10_Junio 2026 (2)
A1: Item | B1: Cuenta Contable | C1: RUC Socio de Negocio | D1: Socio de Negocio | E1: Procedencia | F1: N° Asiento | G1: Libro | H1: Mes | I1: Periodo Contable | J1: Fecha de Transacción | K1: N° Documento | L1: N° Documento Pago | M1: MO | N1: Saldo Origen | O1: Saldo ( S/ ) | P1: Observación Documento | Q1: Observación | R1: Año | S1: F.Emisión
A2: d | B2: 10410013 BBVA CONTINENTAL MN | C2: 20100130204 | D2: BANCO CONTINENTAL | E2: 03. Pago | F2: 0000001963 | G2: Libro Diario | H2: 46023 | I2: 202601 Enero 2026 | J2: 30/01/2026 | K2: AP 0000000257 | L2: AP 0000000257 | M2: S/ | N2: -1 | O2: -1 | P2: COMISIONES BANCARIAS ENERO SOLES | Q2: PAGO DE COMISIONES MENSUALES ENERO 2026 | R2: 2026 | S2: 30/01/2026
A3: d | B3: 10410013 BBVA CONTINENTAL MN | C3: 20100130204 | D3: BANCO CONTINENTAL | E3: 03. Pago | F3: 0000001964 | G3: Libro Diario | H3: 46023 | I3: 202601 Enero 2026 | J3: 30/01/2026 | K3: AP 0000000257 | L3: AP 0000000257 | M3: S/ | N3: -1 | O3: -1 | P3: COMISIONES BANCARIAS ENERO SOLES | Q3: PAGO DE COMISIONES MENSUALES ENERO 2026 | R3: 2026 | S3: 30/01/2026
A4: d | B4: 10410013 BBVA CONTINENTAL MN | C4: 20100130204 | D4: BANCO CONTINENTAL | E4: 03. Pago | F4: 0000001943 | G4: Libro Diario | H4: 46023 | I4: 202601 Enero 2026 | J4: 08/01/2026 | K4: AP 0000000257 | L4: AP 0000000257 | M4: S/ | N4: -3.5 | O4: -3.5 | P4: COMISIONES BANCARIAS ENERO SOLES | Q4: PAGO DE COMISIONES MENSUALES ENERO 2026 | R4: 2026 | S4: 08/01/2026
A5: d | B5: 10410013 BBVA CONTINENTAL MN | C5: 20100130204 | D5: BANCO CONTINENTAL | E5: 03. Pago | F5: 0000001944 | G5: Libro Diario | H5: 46023 | I5: 202601 Enero 2026 | J5: 08/01/2026 | K5: AP 0000000257 | L5: AP 0000000257 | M5: S/ | N5: -3.5 | O5: -3.5 | P5: COMISIONES BANCARIAS ENERO SOLES | Q5: PAGO DE COMISIONES MENSUALES ENERO 2026 | R5: 2026 | S5: 08/01/2026
A6: d | B6: 10410013 BBVA CONTINENTAL MN | C6: 20100130204 | D6: BANCO CONTINENTAL | E6: 03. Pago | F6: 0000001945 | G6: Libro Diario | H6: 46023 | I6: 202601 Enero 2026 | J6: 08/01/2026 | K6: AP 0000000257 | L6: AP 0000000257 | M6: S/ | N6: -3.5 | O6: -3.5 | P6: COMISIONES BANCARIAS ENERO SOLES | Q6: PAGO DE COMISIONES MENSUALES ENERO 2026 | R6: 2026 | S6: 08/01/2026
A7: d | B7: 10410013 BBVA CONTINENTAL MN | C7: 20100130204 | D7: BANCO CONTINENTAL | E7: 03. Pago | F7: 0000001946 | G7: Libro Diario | H7: 46023 | I7: 202601 Enero 2026 | J7: 08/01/2026 | K7: AP 0000000257 | L7: AP 0000000257 | M7: S/ | N7: -3.5 | O7: -3.5 | P7: COMISIONES BANCARIAS ENERO SOLES | Q7: PAGO DE COMISIONES MENSUALES ENERO 2026 | R7: 2026 | S7: 08/01/2026
A8: d | B8: 10410013 BBVA CONTINENTAL MN | C8: 20100130204 | D8: BANCO CONTINENTAL | E8: 03. Pago | F8: 0000001947 | G8: Libro Diario | H8: 46023 | I8: 202601 Enero 2026 | J8: 08/01/2026 | K8: AP 0000000257 | L8: AP 0000000257 | M8: S/ | N8: -3.5 | O8: -3.5 | P8: COMISIONES BANCARIAS ENERO SOLES | Q8: PAGO DE COMISIONES MENSUALES ENERO 2026 | R8: 2026 | S8: 08/01/2026
A9: d | B9: 10410013 BBVA CONTINENTAL MN | C9: 20100130204 | D9: BANCO CONTINENTAL | E9: 03. Pago | F9: 0000001948 | G9: Libro Diario | H9: 46023 | I9: 202601 Enero 2026 | J9: 08/01/2026 | K9: AP 0000000257 | L9: AP 0000000257 | M9: S/ | N9: -3.5 | O9: -3.5 | P9: COMISIONES BANCARIAS ENERO SOLES | Q9: PAGO DE COMISIONES MENSUALES ENERO 2026 | R9: 2026 | S9: 08/01/2026
A10: d | B10: 10410013 BBVA CONTINENTAL MN | C10: 20100130204 | D10: BANCO CONTINENTAL | E10: 03. Pago | F10: 0000001949 | G10: Libro Diario | H10: 46023 | I10: 202601 Enero 2026 | J10: 08/01/2026 | K10: AP 0000000257 | L10: AP 0000000257 | M10: S/ | N10: -3.5 | O10: -3.5 | P10: COMISIONES BANCARIAS ENERO SOLES | Q10: PAGO DE COMISIONES MENSUALES ENERO 2026 | R10: 2026 | S10: 08/01/2026
A11: d | B11: 10410013 BBVA CONTINENTAL MN | C11: 20100130204 | D11: BANCO CONTINENTAL | E11: 03. Pago | F11: 0000001950 | G11: Libro Diario | H11: 46023 | I11: 202601 Enero 2026 | J11: 08/01/2026 | K11: AP 0000000257 | L11: AP 0000000257 | M11: S/ | N11: -3.5 | O11: -3.5 | P11: COMISIONES BANCARIAS ENERO SOLES | Q11: PAGO DE COMISIONES MENSUALES ENERO 2026 | R11: 2026 | S11: 08/01/2026
A12: d | B12: 10410013 BBVA CONTINENTAL MN | C12: 20100130204 | D12: BANCO CONTINENTAL | E12: 03. Pago | F12: 0000001951 | G12: Libro Diario | H12: 46023 | I12: 202601 Enero 2026 | J12: 08/01/2026 | K12: AP 0000000257 | L12: AP 0000000257 | M12: S/ | N12: -3.5 | O12: -3.5 | P12: COMISIONES BANCARIAS ENERO SOLES | Q12: PAGO DE COMISIONES MENSUALES ENERO 2026 | R12: 2026 | S12: 08/01/2026
A13: d | B13: 10410013 BBVA CONTINENTAL MN | C13: 20100130204 | D13: BANCO CONTINENTAL | E13: 03. Pago | F13: 0000001952 | G13: Libro Diario | H13: 46023 | I13: 202601 Enero 2026 | J13: 08/01/2026 | K13: AP 0000000257 | L13: AP 0000000257 | M13: S/ | N13: -3.5 | O13: -3.5 | P13: COMISIONES BANCARIAS ENERO SOLES | Q13: PAGO DE COMISIONES MENSUALES ENERO 2026 | R13: 2026 | S13: 08/01/2026
... A49: d | B49: 10410014 BBVA CONTINENTAL ME | C49: 20100130204 | D49: BANCO CONTINENTAL | E49: 03. Pago | F49: 0000002126 | G49: Libro Diario | H49: 46023 | I49: 202601 Enero 2026 | J49: 30/01/2026 | K49: DP 0000000952 | L49: DP 0000000952 | M49: U$ | N49: -11.35 | O49: -37.97 | P49: ITF ENERO DOLARES | Q49: 01/01 COMISIONES BANCARIAS DE ENERO | R49: 2026 | S49: 30/01/2026
A50: d | B50: 10410014 BBVA CONTINENTAL ME | D50: CORNEJO DAVILA, VANINNA JUISA | E50: 03. Pago | F50: 0000002106 | G50: Libro Diario | H50: 46023 | I50: 202601 Enero 2026 | J50: 26/01/2026 | K50: PR 0000000602 | L50: PR 0000000602 | M50: U$ | N50: -90000 | O50: -302310 | P50: PRESTAMO A VC | Q50: 26/01 PRESTAMO A VC | R50: 2026 | S50: 26/01/2026
A51: d | B51: 10410013 BBVA CONTINENTAL MN | D51: YUPANQUI ARTADI, REYNALDO RICARDO | E51: 03. Pago | F51: 0000002003 | G51: Libro Diario | H51: 46023 | I51: 202601 Enero 2026 | J51: 14/01/2026 | K51: PR 0000000588 | L51: PR 0000000588 | M51: S/ | N51: -210000 | O51: -210000 | P51: PRESTAMO A RYA - CALIDAD Y GESTION | Q51: 14/01 PRESTAMO CALIDAD Y GESTION RY | R51: 2026 | S51: 14/01/2026
A52: d | B52: 10410013 BBVA CONTINENTAL MN | C52: 20601546478 | D52: PANORAMICA TECHNOLOGY S.A.C. | E52: 03. Pago | F52: 0000002049 | G52: Libro Diario | H52: 46023 | I52: 202601 Enero 2026 | J52: 30/01/2026 | K52: AP 0000000261 | L52: AP 0000000261 | M52: S/ | N52: -78735.9 | O52: -78735.9 | P52: ADELANTO PARA CULMINACION DE TRABAJO DE SISTEMA DE COMUNICACIONES | Q52: 30/01 PAGO A PROVEEDORES | R52: 2026 | S52: 30/01/2026
A53: d | B53: 10410014 BBVA CONTINENTAL ME | C53: 20536612972 | D53: CMO GROUP S.A. | E53: 03. Pago | F53: 0000002115 | G53: Libro Diario | H53: 46023 | I53: 202601 Enero 2026 | J53: 30/01/2026 | K53: PR 0000000605 | L53: PR 0000000605 | M53: U$ | N53: -15000 | O53: -50175 | P53: PRESTAMO A CMO // ANCONA | Q53: 30/01 PRESTAMO A CMO: ANCONA | R53: 2026 | S53: 30/01/2026
A54: d | B54: 10410013 BBVA CONTINENTAL MN | C54: 10097521889 | D54: GOMERO ROJAS, GUILLERMO ALBERTO | E54: 03. Pago | F54: 0000002086 | G54: Libro Diario | H54: 46023 | I54: 202601 Enero 2026 | J54: 13/01/2026 | K54: PR 0000000600 | L54: PR 0000000600 | M54: S/ | N54: -45000 | O54: -45000 | P54: PRESTAMO A GG - SERV. GENERALES C&C | Q54: 13/01 PRESTAMO A GG - SERV. GENERALES | R54: 2026 | S54: 13/01/2026
A55: d | B55: 10410014 BBVA CONTINENTAL ME | C55: 20536612972 | D55: CMO GROUP S.A. | E55: 03. Pago | F55: 0000002113 | G55: Libro Diario | H55: 46023 | I55: 202601 Enero 2026 | J55: 30/01/2026 | K55: PR 0000000603 | L55: PR 0000000603 | M55: U$ | N55: -11800 | O55: -39471 | P55: PRESTAMO A CMO // ESTUDIO CARO F002-434 | Q55: 30/01 PRESTAMO A CMO: ESTUDIO CARO | R55: 2026 | S55: 30/01/2026
A56: d | B56: 10410013 BBVA CONTINENTAL MN | C56: 20536612972 | D56: CMO GROUP S.A. | E56: 03. Pago | F56: 0000002020 | G56: Libro Diario | H56: 46023 | I56: 202601 Enero 2026 | J56: 30/01/2026 | K56: PR 0000000590 | L56: PR 0000000590 | M56: S/ | N56: -27652.11 | O56: -27652.11 | P56: PRESTAMO A CMO: PLANILLA ENERO | Q56: 30/01 PRESTAMO A CMO: PLANILLA ENERO 26 | R56: 2026 | S56: 30/01/2026
A57: d | B57: 10410013 BBVA CONTINENTAL MN | C57: 20536612972 | D57: CMO GROUP S.A. | E57: 03. Pago | F57: 0000002078 | G57: Libro Diario | H57: 46023 | I57: 202601 Enero 2026 | J57: 30/01/2026 | K57: PR 0000000596 | L57: PR 0000000596 | M57: S/ | N57: -25000 | O57: -25000 | P57: PRESTAMO A CMO POR PAGO A PROVEEDORES - LBS | Q57: 30/01 PRESTAMO A CMO: PAGO A PROVEEDORES | R57: 2026 | S57: 30/01/2026
A58: d | B58: 10410013 BBVA CONTINENTAL MN | C58: 20536612972 | D58: CMO GROUP S.A. | E58: 03. Pago | F58: 0000002016 | G58: Libro Diario | H58: 46023 | I58: 202601 Enero 2026 | J58: 20/01/2026 | K58: PR 0000000595 | L58: PR 0000000595 | M58: S/ | N58: -20000 | O58: -20000 | P58: PRESTAMO A CMO // IMPUESTOS | Q58: 20/01 PRESTAMO A CMO: IMPUESTOS | R58: 2026 | S58: 20/01/2026
A59: d | B59: 10410013 BBVA CONTINENTAL MN | C59: 20536612972 | D59: CMO GROUP S.A. | E59: 03. Pago | F59: 0000002070 | G59: Libro Diario | H59: 46023 | I59: 202601 Enero 2026 | J59: 30/01/2026 | K59: PR 0000000596 | L59: PR 0000000596 | M59: S/ | N59: -20000 | O59: -20000 | P59: PRESTAMO A CMO POR PAGO A PROVEEDORES - LBS | Q59: 30/01 PRESTAMO A CMO: PAGO A PROVEEDORES | R59: 2026 | S59: 30/01/2026
A60: d | B60: 10410013 BBVA CONTINENTAL MN | C60: 20536612972 | D60: CMO GROUP S.A. | E60: 03. Pago | F60: 0000002071 | G60: Libro Diario | H60: 46023 | I60: 202601 Enero 2026 | J60: 30/01/2026 | K60: PR 0000000596 | L60: PR 0000000596 | M60: S/ | N60: -20000 | O60: -20000 | P60: PRESTAMO A CMO POR PAGO A PROVEEDORES - LBS | Q60: 30/01 PRESTAMO A CMO: PAGO A PROVEEDORES | R60: 2026 | S60: 30/01/2026
A61: d | B61: 10410013 BBVA CONTINENTAL MN | C61: 20536612972 | D61: CMO GROUP S.A. | E61: 03. Pago | F61: 0000002079 | G61: Libro Diario | H61: 46023 | I61: 202601 Enero 2026 | J61: 30/01/2026 | K61: PR 0000000596 | L61: PR 0000000596 | M61: S/ | N61: -20000 | O61: -20000 | P61: PRESTAMO A CMO POR PAGO A PROVEEDORES - LBS | Q61: 30/01 PRESTAMO A CMO: PAGO A PROVEEDORES | R61: 2026 | S61: 30/01/2026
A62: d | B62: 10410013 BBVA CONTINENTAL MN | C62: 20431115825 | D62: PACIFICO SA ENT PRESTADORA DE SALUD | E62: 03. Pago | F62: 0000002043 | G62: Libro Diario | H62: 46023 | I62: 202601 Enero 2026 | J62: 30/01/2026 | K62: F F027-01053589 | L62: F F027-01053589 | M62: S/ | N62: -18563.68 | O62: -18563.68 | P62: SEGURO EPS // A/COB 9985023 // DOC R-4344398 // VIGENCIA 01/01/2026 AL 31/01/2026 | Q62: 30/01 PAGO A PROVEEDORES | R62: 2026 | S62: 30/01/2026
A63: d | B63: 10410013 BBVA CONTINENTAL MN | C63: 20536612972 | D63: CMO GROUP S.A. | E63: 03. Pago | F63: 0000002074 | G63: Libro Diario | H63: 46023 | I63: 202601 Enero 2026 | J63: 30/01/2026 | K63: PR 0000000596 | L63: PR 0000000596 | M63: S/ | N63: -16875 | O63: -16875 | P63: PRESTAMO A CMO POR PAGO A PROVEEDORES - LBS | Q63: 30/01 PRESTAMO A CMO: PAGO A PROVEEDORES | R63: 2026 | S63: 30/01/2026
... A124: d | B124: 10410013 BBVA CONTINENTAL MN | C124: 10088768197 | D124: BALAREZO ELIAS DE TIRADO, ANA GABRIELA | E124: 03. Pago | F124: 0000002004 | G124: Libro Diario | H124: 46023 | I124: 202601 Enero 2026 | J124: 19/01/2026 | K124: R 0000000001 | L124: R 0000000001 | M124: S/ | N124: -624.33 | O124: -624.33 | P124: CAJA CHICA - INTEGRAL // SEGUN CORREO 19.09.24 | Q124: 19/01 REEMBOLSO CAJA CHICA | R124: 2026 | S124: 19/01/2026
A125: d | B125: 10410013 BBVA CONTINENTAL MN | C125: 10000620471 | D125: VELASQUEZ URREGO, JUAN CARLOS | E125: 03. Pago | F125: 0000002051 | G125: Libro Diario | H125: 46023 | I125: 202601 Enero 2026 | J125: 30/01/2026 | M125: S/ | N125: -611.79 | O125: -611.79 | P125: 30/01 REEMBOLSO A COLABORADORES | Q125: 30/01 REEMBOLSO A COLABORADORES | R125: 2026 | S125: 30/01/2026
A126: d | B126: 10410013 BBVA CONTINENTAL MN | C126: 10771013193 | D126: CCORISAPRA MUÑOZ, ALEXNIEL | E126: 03. Pago | F126: 0000000130 | G126: Libro Diario | H126: 46023 | I126: 202601 Enero 2026 | J126: 30/01/2026 | K126: AP 0000000240 | L126: AP 0000000240 | M126: S/ | N126: -600 | O126: -600 | P126: ADELANTO POR SERVICIO ENERO 2026 | Q126: PAGO DE SERV. HONORARIOS DM Y AC ENERO 2026 | R126: 2026 | S126: 30/01/2026
A127: d | B127: 10410013 BBVA CONTINENTAL MN | C127: 10088768197 | D127: BALAREZO ELIAS DE TIRADO, ANA GABRIELA | E127: 03. Pago | F127: 0000002146 | G127: Libro Diario | H127: 46023 | I127: 202601 Enero 2026 | J127: 30/01/2026 | K127: R 0000000001 | L127: R 0000000001 | M127: S/ | N127: -581.9 | O127: -581.9 | P127: CAJA CHICA - INTEGRAL // SEGUN CORREO 19.09.24 | Q127: 30/01 REEMBOLSO DE CAJA CHICA | R127: 2026 | S127: 30/01/2026
A128: d | B128: 10410013 BBVA CONTINENTAL MN | C128: 20418896915 | D128: MAPFRE PERU COMPAÑIA DE SEGUROS Y REASEGUROS | E128: 03. Pago | F128: 0000002039 | G128: Libro Diario | H128: 46023 | I128: 202601 Enero 2026 | J128: 30/01/2026 | K128: F F050-00749220 | L128: F F050-00749220 | M128: S/ | N128: -580.04 | O128: -580.04 | P128: SEGURO SCTR PENSIONES VALIDO DE 01/01/2026 AL 31/01/2026 - CT CANCELACION RECIBO 167389355 | Q128: 30/01 PAGO A PROVEEDORES | R128: 2026 | S128: 30/01/2026
A129: d | B129: 10410013 BBVA CONTINENTAL MN | C129: 20536612972 | D129: CMO GROUP S.A. | E129: 03. Pago | F129: 0000002065 | G129: Libro Diario | H129: 46023 | I129: 202601 Enero 2026 | J129: 30/01/2026 | K129: PR 0000000596 | L129: PR 0000000596 | M129: S/ | N129: -457.21 | O129: -457.21 | P129: PRESTAMO A CMO POR PAGO A PROVEEDORES - LBS | Q129: 30/01 PRESTAMO A CMO: PAGO A PROVEEDORES | R129: 2026 | S129: 30/01/2026
A130: d | B130: 10410013 BBVA CONTINENTAL MN | C130: 10422397596 | D130: TALLEDO GILVONIO MANUEL OMAR | E130: 03. Pago | F130: 0000000039 | G130: Libro Diario | H130: 46023 | I130: 202601 Enero 2026 | J130: 08/01/2026 | K130: F E001-00000018 | L130: F E001-00000018 | M130: S/ | N130: -447 | O130: -447 | P130: ADMINISTRACION DE REDES SOCIALES - SEPTIEMBRE - OCTUBRE 2025 + DISEÑO DE BROCHURE CORPORATIVO | Q130: PAGO DE DETRACCION TALLEDO E001-18 | R130: 2026 | S130: 08/01/2026
A131: d | B131: 10410014 BBVA CONTINENTAL ME | C131: 20100130204 | D131: BANCO CONTINENTAL | E131: 03. Pago | F131: 0000002118 | G131: Libro Diario | H131: 46023 | I131: 202601 Enero 2026 | J131: 26/01/2026 | K131: AP 0000000263 | L131: AP 0000000263 | M131: U$ | N131: -123.5 | O131: -414.84 | P131: COMISIONES BBVA DOLARES | Q131: 26/01 COMISIONES BANCARIAS DE ENERO | R131: 2026 | S131: 26/01/2026
A132: d | B132: 10410013 BBVA CONTINENTAL MN | C132: 10097521889 | D132: GOMERO ROJAS, GUILLERMO ALBERTO | E132: 03. Pago | F132: 0000002027 | G132: Libro Diario | H132: 46023 | I132: 202601 Enero 2026 | J132: 20/01/2026 | K132: PR 0000000599 | L132: PR 0000000599 | M132: S/ | N132: -413.51 | O132: -413.51 | P132: PRESTAMO A GG - LUMINARIAS | Q132: 20/01 PRESTAMO A GG - LUMINARIAS | R132: 2026 | S132: 20/01/2026
A133: d | B133: 10410013 BBVA CONTINENTAL MN | C133: 20536612972 | D133: CMO GROUP S.A. | E133: 03. Pago | F133: 0000002066 | G133: Libro Diario | H133: 46023 | I133: 202601 Enero 2026 | J133: 30/01/2026 | K133: PR 0000000596 | L133: PR 0000000596 | M133: S/ | N133: -387.7 | O133: -387.7 | P133: PRESTAMO A CMO POR PAGO A PROVEEDORES - LBS | Q133: 30/01 PRESTAMO A CMO: PAGO A PROVEEDORES | R133: 2026 | S133: 30/01/2026
A134: d | B134: 10410013 BBVA CONTINENTAL MN | C134: 20536612972 | D134: CMO GROUP S.A. | E134: 03. Pago | F134: 0000002069 | G134: Libro Diario | H134: 46023 | I134: 202601 Enero 2026 | J134: 30/01/2026 | K134: PR 0000000596 | L134: PR 0000000596 | M134: S/ | N134: -387.7 | O134: -387.7 | P134: PRESTAMO A CMO POR PAGO A PROVEEDORES - LBS | Q134: 30/01 PRESTAMO A CMO: PAGO A PROVEEDORES | R134: 2026 | S134: 30/01/2026
A135: d | B135: 10410013 BBVA CONTINENTAL MN | C135: 20107167481 | D135: FOTO PLUS S.R.L. | E135: 03. Pago | F135: 0000002050 | G135: Libro Diario | H135: 46023 | I135: 202601 Enero 2026 | J135: 30/01/2026 | K135: AP 0000000262 | L135: AP 0000000262 | M135: S/ | N135: -380 | O135: -380 | P135: ADELANTO A PROVEEDOR SEGUN EECC | Q135: 30/01 PAGO A PROVEEDORES | R135: 2026 | S135: 30/01/2026
A136: d | B136: 10410013 BBVA CONTINENTAL MN | C136: 20431115825 | D136: PACIFICO SA ENT PRESTADORA DE SALUD | E136: 03. Pago | F136: 0000002041 | G136: Libro Diario | H136: 46023 | I136: 202601 Enero 2026 | J136: 30/01/2026 | K136: ND FD12-00200362 | L136: ND FD12-00200362 | M136: S/ | N136: -376.87 | O136: -376.87 | P136: SEGURO PACIFICO EPS- SALUD// POLIZA: 128583 // VIG 01/11/2025 AL 30/11/2025 REF: F027-01035425 DEL 07.11.25 | Q136: 30/01 PAGO A PROVEEDORES | R136: 2026 | S136: 30/01/2026
A137: d | B137: 10410013 BBVA CONTINENTAL MN | C137: 10422397596 | D137: TALLEDO GILVONIO MANUEL OMAR | E137: 03. Pago | F137: 0000000037 | G137: Libro Diario | H137: 46023 | I137: 202601 Enero 2026 | J137: 08/01/2026 | K137: F E001-00000017 | L137: F E001-00000017 | M137: S/ | N137: -305 | O137: -305 | P137: ADMINISTRACION DE REDES SOCIALES - AGOSTO - SEPTIEMBRE 2025 | Q137: PAGO DE DETRACCION TALLEDO E001-17 | R137: 2026 | S137: 08/01/2026
... A141: d | B141: 10410014 BBVA CONTINENTAL ME | C141: 20257094465 | D141: AGENCIA DE ADUANA MACROMAR S.A. | E141: 03. Pago | F141: 0000002104 | G141: Libro Diario | H141: 46023 | I141: 202601 Enero 2026 | J141: 02/01/2026 | K141: AP 0000000264 | L141: AP 0000000264 | M141: U$ | N141: -64.9 | O141: -218.58 | P141: ADELANTO - MACROMAR AGENCIA DE ADUANAS - IMPORTACION DE ESCULTURA | Q141: 02/01 ADELANTO POR TRANSPORTE DE ESCULTURA | R141: 2026 | S141: 02/01/2026
A142: d | B142: 10410013 BBVA CONTINENTAL MN | D142: YUPANQUI ARTADI, REYNALDO RICARDO | E142: 03. Pago | F142: 0000002053 | G142: Libro Diario | H142: 46023 | I142: 202601 Enero 2026 | J142: 30/01/2026 | M142: S/ | N142: -195.8 | O142: -195.8 | P142: 30/01 REEMBOLSO A COLABORADORES | Q142: 30/01 REEMBOLSO A COLABORADORES | R142: 2026 | S142: 30/01/2026
A143: d | B143: 10410013 BBVA CONTINENTAL MN | C143: 20605246240 | D143: NEXUS CARGO S.A.C. | E143: 03. Pago | F143: 0000002033 | G143: Libro Diario | H143: 46023 | I143: 202601 Enero 2026 | J143: 30/01/2026 | K143: F E001-00002340 | L143: F E001-00002340 | M143: S/ | N143: -188.8 | O143: -188.8 | P143: SERVICIO DE TRASLADO DE CUADRO EN VAN EL 29 DE ENERO 2026-DESDE OFICINA MANUEL OLGUIN HACIA CERROS DE CAMACHO. | Q143: 30/01 PAGO A PROVEEDORES | R143: 2026 | S143: 30/01/2026
A144: d | B144: 10410013 BBVA CONTINENTAL MN | C144: 20536612972 | D144: CMO GROUP S.A. | E144: 03. Pago | F144: 0000002068 | G144: Libro Diario | H144: 46023 | I144: 202601 Enero 2026 | J144: 30/01/2026 | K144: PR 0000000596 | L144: PR 0000000596 | M144: S/ | N144: -188.23 | O144: -188.23 | P144: PRESTAMO A CMO POR PAGO A PROVEEDORES - LBS | Q144: 30/01 PRESTAMO A CMO: PAGO A PROVEEDORES | R144: 2026 | S144: 30/01/2026
A145: d | B145: 10410013 BBVA CONTINENTAL MN | C145: 20100130204 | D145: BANCO CONTINENTAL | E145: 03. Pago | F145: 0000002089 | G145: Libro Diario | H145: 46023 | I145: 202601 Enero 2026 | J145: 30/01/2026 | K145: DP 0000000889 | L145: DP 0000000889 | M145: S/ | N145: -152.7 | O145: -152.7 | P145: ITF + COMISION ENERO SOLES | Q145: 30/01 GASTOS BANCARIOS - ITF | R145: 2026 | S145: 30/01/2026
A146: d | B146: 10410013 BBVA CONTINENTAL MN | C146: 20609325543 | D146: VPX CLUB 108 S.A.C. | E146: 03. Pago | F146: 0000000056 | G146: Libro Diario | H146: 46023 | I146: 202601 Enero 2026 | J146: 08/01/2026 | K146: F FCL1-00001839 | L146: F FCL1-00001839 | M146: S/ | N146: -147 | O146: -147 | P146: GASTOS DIVERSOS - EVENTO DE FIN DE AÑO 2025 (18% ATENCION AL PERSONAL Y 82% PUBLICIDAD) | Q146: PAGO DE DETRACCION FCL1-1839 | R146: 2026 | S146: 08/01/2026
A147: d | B147: 10410013 BBVA CONTINENTAL MN | C147: 20332970411 | D147: PACIFICO COMPAÑIA DE SEGUROS Y REASEGUROS | E147: 03. Pago | F147: 0000002037 | G147: Libro Diario | H147: 46023 | I147: 202601 Enero 2026 | J147: 30/01/2026 | K147: F F091-00103013 | L147: F F091-00103013 | M147: S/ | N147: -119.98 | O147: -119.98 | P147: SEGURO FOLA // DOC AC 93826460 // POLIZA 21474364 // VIGENCIA 01/01/2026 AL 31/01/2026. | Q147: 30/01 PAGO A PROVEEDORES | R147: 2026 | S147: 30/01/2026
A148: d | B148: 10410013 BBVA CONTINENTAL MN | C148: 20600964608 | D148: SERVICIOS GENERALES DE CONSTRUCCION C & C S.A.C. | E148: 03. Pago | F148: 0000000033 | G148: Libro Diario | H148: 46023 | I148: 202601 Enero 2026 | J148: 08/01/2026 | K148: F E001-00000282 | L148: F E001-00000282 | M148: S/ | N148: -78 | O148: -78 | P148: CAMBIO DE REPUESTO DE MANIJA, VASTAGO Y EMBOLO DE FLUXOMETRO DE BAÑO DE VARONES. | Q148: PAGO DE DETRACCIONES | R148: 2026 | S148: 08/01/2026
A149: d | B149: 10410013 BBVA CONTINENTAL MN | D149: QUINO DUEÑAS, KIMBERLY JHOANA | E149: 03. Pago | F149: 0000002055 | G149: Libro Diario | H149: 46023 | I149: 202601 Enero 2026 | J149: 30/01/2026 | M149: S/ | N149: -68.2 | O149: -68.2 | P149: 30/01 REEMBOLSO A COLABORADORES | Q149: 30/01 REEMBOLSO A COLABORADORES | R149: 2026 | S149: 30/01/2026
A150: d | B150: 10410013 BBVA CONTINENTAL MN | D150: VILLEGAS TINEO, NICOLASA | E150: 03. Pago | F150: 0000002058 | G150: Libro Diario | H150: 46023 | I150: 202601 Enero 2026 | J150: 30/01/2026 | K150: DP 0000000901 | L150: DP 0000000901 | M150: S/ | N150: -49 | O150: -49 | P150: RECOJO DE LUMINARIAS | Q150: 30/01 REEMBOLSO A COLABORADORES | R150: 2026 | S150: 30/01/2026
A151: d | B151: 10410013 BBVA CONTINENTAL MN | C151: 10755406576 | D151: VERA OCAS, ALEXANDRA MARIBEL | E151: 03. Pago | F151: 0000002047 | G151: Libro Diario | H151: 46023 | I151: 202601 Enero 2026 | J151: 30/01/2026 | K151: DP 0000000902 | L151: DP 0000000902 | M151: S/ | N151: -45 | O151: -45 | P151: MOVILIDAD DESDE OFICINA - NOTARIA (RECOJO DE ESCRITO LEGALIZADO) // NOTARIA - SUNAT (PRESENTACION DE ESCRITO) // OFICINA - NOTARIA TELLO (LEGALIZACION DE LIBROS CONTABLES) // NOTARIA TELLO - MANUEL OLGUIN (RETORNO A LA OFICINA) | Q151: 30/01 PAGO A PROVEEDORES | R151: 2026 | S151: 30/01/2026
A152: d | B152: 10410013 BBVA CONTINENTAL MN | C152: 10755406576 | D152: VERA OCAS, ALEXANDRA MARIBEL | E152: 03. Pago | F152: 0000002047 | G152: Libro Diario | H152: 46023 | I152: 202601 Enero 2026 | J152: 30/01/2026 | K152: DP 0000000903 | L152: DP 0000000903 | M152: S/ | N152: -45 | O152: -45 | P152: MOVILIDAD DESDE OFICINA - BBVA SANTA CRUZ MIRAFLORES (DOCUMENTOS ACTUALIZADOS) // SANTA CRUZ 695 - SANTA CRUZ 381 (COPIA DE TESTIMONIO - ESCRITURA PUBLICA) // SANTA CRUZ MIRAFLORES - OFICINA SURCO (RETORNO A LA OFICINA) | Q152: 30/01 PAGO A PROVEEDORES | R152: 2026 | S152: 30/01/2026
A153: d | B153: 10410013 BBVA CONTINENTAL MN | C153: 10755406576 | D153: VERA OCAS, ALEXANDRA MARIBEL | E153: 03. Pago | F153: 0000002047 | G153: Libro Diario | H153: 46023 | I153: 202601 Enero 2026 | J153: 30/01/2026 | K153: DP 0000000904 | L153: DP 0000000904 | M153: S/ | N153: -45 | O153: -45 | P153: MOVILIDAD DESDE OFICINA OLGUIN - LAS AZUCENAS SURCO (DOCUMENTACION DE INTEGRAL EN ALMACEN) // LAS AZUCENAS SURCO - OFICINA SURCO (RETORNO A LA OFICINA CON DOCUMENTOS DE INTEGRAL). | Q153: 30/01 PAGO A PROVEEDORES | R153: 2026 | S153: 30/01/2026
A154: d | B154: 10410013 BBVA CONTINENTAL MN | C154: 10755406576 | D154: VERA OCAS, ALEXANDRA MARIBEL | E154: 03. Pago | F154: 0000002047 | G154: Libro Diario | H154: 46023 | I154: 202601 Enero 2026 | J154: 30/01/2026 | K154: DP 0000000905 | L154: DP 0000000905 | M154: S/ | N154: -45 | O154: -45 | P154: MOVILIDAD DESDE OFICINA SURCO - SUNAT SAN ISIDRO (PRESENTACION DE DOCUMENTOS SUNAT) // SUNAT SAN ISIDRO - OFICINA SURCO (RETORNO A LA OFICINA) | Q154: 30/01 PAGO A PROVEEDORES | R154: 2026 | S154: 30/01/2026
A155: d | B155: 10410013 BBVA CONTINENTAL MN | C155: 10755406576 | D155: VERA OCAS, ALEXANDRA MARIBEL | E155: 03. Pago | F155: 0000002047 | G155: Libro Diario | H155: 46023 | I155: 202601 Enero 2026 | J155: 30/01/2026 | K155: DP 0000000906 | L155: DP 0000000906 | M155: S/ | N155: -45 | O155: -45 | P155: MOVILIDAD DESDE SURCO - AV. EL DERBY (ENTREGA DE DOCUMENTOS EN EL DERBY) // SURCO - OFICINA (IMPRESIONES OFICINAS MANUEL OLGUIN) // EL DERBY - NOTARIA PEREZ TELLO (LEGALIZACION DE FIRMA) // NOTARIA PEREZ TELLO - OFICINA SURCO (RETORNO A LA OFICINA) | Q155: 30/01 PAGO A PROVEEDORES | R155: 2026 | S155: 30/01/2026
A156: d | B156: 10410013 BBVA CONTINENTAL MN | C156: 10755406576 | D156: VERA OCAS, ALEXANDRA MARIBEL | E156: 03. Pago | F156: 0000002047 | G156: Libro Diario | H156: 46023 | I156: 202601 Enero 2026 | J156: 30/01/2026 | K156: DP 0000000907 | L156: DP 0000000907 | M156: S/ | N156: -45 | O156: -45 | P156: MOVILIDAD DESDE OFICINA SURCO - SAN ISIDRO (FIRMAR FORMULARIOS CON EL DR. RAMIREZ) // SAN ISIDRO (LLEVAR FORMULARIOS A CRBC) // SAN ISIDRO - OFICINA SURCO (RETORNO A LA OFICINA) | Q156: 30/01 PAGO A PROVEEDORES | R156: 2026 | S156: 30/01/2026
A157: d | B157: 10410013 BBVA CONTINENTAL MN | C157: 10755406576 | D157: VERA OCAS, ALEXANDRA MARIBEL | E157: 03. Pago | F157: 0000002047 | G157: Libro Diario | H157: 46023 | I157: 202601 Enero 2026 | J157: 30/01/2026 | K157: DP 0000000908 | L157: DP 0000000908 | M157: S/ | N157: -45 | O157: -45 | P157: MOVILIDAD DESDE OFICINA SURCO - BBVA SANTA CRUZ MIRAFLORES (RECOGER DOCUMENTACION) // SANTA CRUZ 695 - SANTA CRUZ 381 (IMPRIMIR Y ESCANEAR) // BBVA SANTA CRUZ - OFICINA SURCO (RETORNO A LA OFICINA). | Q157: 30/01 PAGO A PROVEEDORES | R157: 2026 | S157: 30/01/2026
A158: d | B158: 10410013 BBVA CONTINENTAL MN | C158: 10755406576 | D158: VERA OCAS, ALEXANDRA MARIBEL | E158: 03. Pago | F158: 0000002047 | G158: Libro Diario | H158: 46023 | I158: 202601 Enero 2026 | J158: 30/01/2026 | K158: DP 0000000909 | L158: DP 0000000909 | M158: S/ | N158: -45 | O158: -45 | P158: MOVILIDAD DESDE OFICINA SURCO - LINCE (FIRMAR NUEVOS FORMATOS CON EL DR.RAMIREZ) // SAN ISIDRO (ENTREGAR NUEVOS FORMATOS A CRBC) // SAN ISIDRO - OFICINA SURCO (RETORNO A OFICINA) | Q158: 30/01 PAGO A PROVEEDORES | R158: 2026 | S158: 30/01/2026
A159: d | B159: 10410013 BBVA CONTINENTAL MN | C159: 10755406576 | D159: VERA OCAS, ALEXANDRA MARIBEL | E159: 03. Pago | F159: 0000002047 | G159: Libro Diario | H159: 46023 | I159: 202601 Enero 2026 | J159: 30/01/2026 | K159: DP 0000000910 | L159: DP 0000000910 | M159: S/ | N159: -45 | O159: -45 | P159: MOVILIDAD DESDE OFICINA SURCO OLGUIN - LAS AZUCENAS SURCO (DOCUMENTACION DE INTEGRAL EN ALMACEN) // LAS AZUCENAS SURCO - OFICINA SURCO (RETORNO A OFICINA CON DOCUMENTACION DE INTEGRAL). | Q159: 30/01 PAGO A PROVEEDORES | R159: 2026 | S159: 30/01/2026
A160: d | B160: 10410013 BBVA CONTINENTAL MN | C160: 10755406576 | D160: VERA OCAS, ALEXANDRA MARIBEL | E160: 03. Pago | F160: 0000002047 | G160: Libro Diario | H160: 46023 | I160: 202601 Enero 2026 | J160: 30/01/2026 | K160: DP 0000000911 | L160: DP 0000000911 | M160: S/ | N160: -45 | O160: -45 | P160: MOVILIDAD DESDE OFICINA SURCO - SUNAT SAN ISIDRO JUAN DE ARONA 887 (ENTREGA DE USB EN SUNAT PARA COMPLEMENTAR DOCUMENTACION ENTREGADA) // SUNAT SAN ISIDRO - OFICINA SURCO (RETORNO A LA OFICINA) | Q160: 30/01 PAGO A PROVEEDORES | R160: 2026 | S160: 30/01/2026
A161: d | B161: 10410013 BBVA CONTINENTAL MN | C161: 10755406576 | D161: VERA OCAS, ALEXANDRA MARIBEL | E161: 03. Pago | F161: 0000002047 | G161: Libro Diario | H161: 46023 | I161: 202601 Enero 2026 | J161: 30/01/2026 | K161: DP 0000000912 | L161: DP 0000000912 | M161: S/ | N161: -45 | O161: -45 | P161: MOVILIDAD DESDE OFICINA OLGUIN - AV. EL DERBY (RECOGIENDO DOCUMENTACION) // AV. EL DERBY - OLGUIN (ESCANEO DE DOCUMENTACION) // OFICINA SURCO - NOTARIA PEREZ TELLO (LEGALIZACION DE FIRMA) // NOTARIA PEREZ TELLO - OFICINA SURCO (RETORNO A OFICINA) | Q161: 30/01 PAGO A PROVEEDORES | R161: 2026 | S161: 30/01/2026
A162: d | B162: 10410013 BBVA CONTINENTAL MN | C162: 10755406576 | D162: VERA OCAS, ALEXANDRA MARIBEL | E162: 03. Pago | F162: 0000002047 | G162: Libro Diario | H162: 46023 | I162: 202601 Enero 2026 | J162: 30/01/2026 | K162: DP 0000000913 | L162: DP 0000000913 | M162: S/ | N162: -45 | O162: -45 | P162: MOVILIDAD DESDE OFICINA DE SURCO - SAN ISIDRO (FIRMAR FORMULARIOS CON EL DR. RAMIREZ ) // SAN ISIDRO (LLEVAR FORMULARIOS A CRBC) // SAN ISIDRO - OFICINA SURCO (RETORNO A LA OFICINA) | Q162: 30/01 PAGO A PROVEEDORES | R162: 2026 | S162: 30/01/2026
A163: d | B163: 10410013 BBVA CONTINENTAL MN | C163: 10755406576 | D163: VERA OCAS, ALEXANDRA MARIBEL | E163: 03. Pago | F163: 0000002047 | G163: Libro Diario | H163: 46023 | I163: 202601 Enero 2026 | J163: 30/01/2026 | K163: DP 0000000914 | L163: DP 0000000914 | M163: S/ | N163: -45 | O163: -45 | P163: MOVILIDAD DESDE OFICINA OLGUIN - LAS AZUCENAS SURCO (LLEVANDO DOCUMENTACION DE INTEGRAL A ALMACEN) // LAS AZUCENAS - OFICINA OLGUIN (RETORNO A OFICINA) | Q163: 30/01 PAGO A PROVEEDORES | R163: 2026 | S163: 30/01/2026
A164: d | B164: 10410013 BBVA CONTINENTAL MN | D164: VILLEGAS TINEO, DANIEL | E164: 03. Pago | F164: 0000002057 | G164: Libro Diario | H164: 46023 | I164: 202601 Enero 2026 | J164: 30/01/2026 | K164: DP 0000000900 | L164: DP 0000000900 | M164: S/ | N164: -15 | O164: -15 | P164: COMISION ENCARGO CASA GG * TRAMITES | Q164: 30/01 REEMBOLSO A COLABORADORES | R164: 2026 | S164: 30/01/2026
A165: d | B165: 10410013 BBVA CONTINENTAL MN | C165: 10755406576 | D165: VERA OCAS, ALEXANDRA MARIBEL | E165: 03. Pago | F165: 0000002047 | G165: Libro Diario | H165: 46023 | I165: 202601 Enero 2026 | J165: 30/01/2026 | K165: DP 0000000915 | L165: DP 0000000915 | M165: S/ | N165: -15 | O165: -15 | P165: MOVILIDAD DESDE OLGUIN - AV. EL DERBY (RECOGIENDO DOCUMENTACION DEL DERBY) // AV. EL DERBY - OFICINA OLGUIN (RETORNO A LA OFICINA PARA ESCANEAR DOCUMENTACION) | Q165: 30/01 PAGO A PROVEEDORES | R165: 2026 | S165: 30/01/2026
A166: d | B166: 10410014 BBVA CONTINENTAL ME | E166: 14. Diferencia de cambio - Cuentas | F166: 0000000224 | G166: Diferencia de Cambio | H166: 46023 | I166: 202601 Enero 2026 | J166: 31/01/2026 | M166: U$ | N166: 0 | O166: -2353.2 | P166: Diferencia de cambio - Por Cuenta | Q166: Diferencia de cambio - Por Cuenta | R166: 2026 | S166: 31/01/2026
A167: d | B167: 10410013 BBVA CONTINENTAL MN | C167: 20100130204 | D167: BANCO CONTINENTAL | E167: 03. Pago | F167: 0000000492 | G167: Libro Diario | H167: 46054 | I167: 202602 Febrero 2026 | J167: 27/02/2026 | K167: F FB26-26160450 | L167: F FB26-26160450 | M167: S/ | N167: -3.5 | O167: -3.5 | P167: COMISIONES 001104860100203867 COMISIONES DE MANTENIMIENTO/000005128 // COMISIONES 001104860100203867 ENVIO DE EXTRACTO DE MOVIMIENTO/000005129 | Q167: 27/02 COMISIONES BANCARIAS FEBRERO 2026 | R167: 2026 | S167: 27/02/2026
A168: d | B168: 10410013 BBVA CONTINENTAL MN | C168: 20100130204 | D168: BANCO CONTINENTAL | E168: 03. Pago | F168: 0000000494 | G168: Libro Diario | H168: 46054 | I168: 202602 Febrero 2026 | J168: 27/02/2026 | K168: F FB26-26160450 | L168: F FB26-26160450 | M168: S/ | N168: -40 | O168: -40 | P168: COMISIONES 001104860100203867 COMISIONES DE MANTENIMIENTO/000005128 // COMISIONES 001104860100203867 ENVIO DE EXTRACTO DE MOVIMIENTO/000005129 | Q168: 27/02 COMISIONES BANCARIAS FEBRERO 2026 | R168: 2026 | S168: 27/02/2026
A169: d | B169: 10410013 BBVA CONTINENTAL MN | C169: 20100130204 | D169: BANCO CONTINENTAL | E169: 03. Pago | F169: 0000000478 | G169: Libro Diario | H169: 46054 | I169: 202602 Febrero 2026 | J169: 10/02/2026 | K169: F FB25-25926161 | L169: F FB25-25926161 | M169: S/ | N169: -50 | O169: -50 | P169: COMISIONES 001104860100203867 COMSIONES TRASPADO O/P 000004996 | Q169: 10/02 COMISIONES BANCARIAS FEBRERO 2026 | R169: 2026 | S169: 10/02/2026
A170: d | B170: 10410013 BBVA CONTINENTAL MN | C170: 20100130204 | D170: BANCO CONTINENTAL | E170: 03. Pago | F170: 0000000452 | G170: Libro Diario | H170: 46054 | I170: 202602 Febrero 2026 | J170: 03/02/2026 | K170: F FC04-04824130 | L170: F FC04-04824130 | M170: S/ | N170: -40 | O170: -40 | P170: COMISIONES 001104860100203867 POR USO DE CANAL/000000002 | Q170: 03/02 COMISIONES BANCARIAS FEBRERO 2026 | R170: 2026 | S170: 03/02/2026
A171: d | B171: 10410014 BBVA CONTINENTAL ME | C171: 20100130204 | D171: BANCO CONTINENTAL | E171: 03. Pago | F171: 0000000619 | G171: Libro Diario | H171: 46054 | I171: 202602 Febrero 2026 | J171: 27/02/2026 | K171: F FB26-26160451 | L171: F FB26-26160451 | M171: U$ | N171: -1.3 | O171: -4.37 | P171: COMISIONES 001104860100203875 COMISION DE MANTENIMIENTO/000000751 // COMISIONES 001104860100203875 ENVIO DE EXTRACTO DE MOVIMIENTO/000000752. | Q171: COMISIONES BANCARIAS FEBERO | R171: 2026 | S171: 27/02/2026
A172: d | B172: 10410014 BBVA CONTINENTAL ME | C172: 20100130204 | D172: BANCO CONTINENTAL | E172: 03. Pago | F172: 0000000617 | G172: Libro Diario | H172: 46054 | I172: 202602 Febrero 2026 | J172: 27/02/2026 | K172: F FB26-26160451 | L172: F FB26-26160451 | M172: U$ | N172: -14 | O172: -47.04 | P172: COMISIONES 001104860100203875 COMISION DE MANTENIMIENTO/000000751 // COMISIONES 001104860100203875 ENVIO DE EXTRACTO DE MOVIMIENTO/000000752. | Q172: COMISIONES BANCARIAS FEBERO | R172: 2026 | S172: 27/02/2026
A173: d | B173: 10410013 BBVA CONTINENTAL MN | C173: 20100130204 | D173: BANCO CONTINENTAL | E173: 03. Pago | F173: 0000000482 | G173: Libro Diario | H173: 46054 | I173: 202602 Febrero 2026 | J173: 23/02/2026 | K173: F FF18-18833454 | L173: F FF18-18833454 | M173: S/ | N173: -4.3 | O173: -4.3 | P173: COMISIONES 00219113140399000050 EMISION TRANSF. CCE 0002520020/0011-0486-0100203867 // COMISIONES 00219113140399000050 EMISION TRANSF. CCE 0002520021/0011-0486-0100203867 // COMISIONES 00219100248967008054 EMISION TRANSF. CCE 0002520022/0011-0486-0100203867 | Q173: 23/02 COMISIONES BANCARIAS FEBRERO 2026 | R173: 2026 | S173: 23/02/2026
A174: d | B174: 10410013 BBVA CONTINENTAL MN | C174: 20100130204 | D174: BANCO CONTINENTAL | E174: 03. Pago | F174: 0000000484 | G174: Libro Diario | H174: 46054 | I174: 202602 Febrero 2026 | J174: 23/02/2026 | K174: F FF18-18833454 | L174: F FF18-18833454 | M174: S/ | N174: -4.3 | O174: -4.3 | P174: COMISIONES 00219113140399000050 EMISION TRANSF. CCE 0002520020/0011-0486-0100203867 // COMISIONES 00219113140399000050 EMISION TRANSF. CCE 0002520021/0011-0486-0100203867 // COMISIONES 00219100248967008054 EMISION TRANSF. CCE 0002520022/0011-0486-0100203867 | Q174: COMISIONES BANCARIAS FEBRERO 2026 | R174: 2026 | S174: 23/02/2026
A175: d | B175: 10410013 BBVA CONTINENTAL MN | C175: 20100130204 | D175: BANCO CONTINENTAL | E175: 03. Pago | F175: 0000000486 | G175: Libro Diario | H175: 46054 | I175: 202602 Febrero 2026 | J175: 23/02/2026 | K175: F FF18-18833454 | L175: F FF18-18833454 | M175: S/ | N175: -4.3 | O175: -4.3 | P175: COMISIONES 00219113140399000050 EMISION TRANSF. CCE 0002520020/0011-0486-0100203867 // COMISIONES 00219113140399000050 EMISION TRANSF. CCE 0002520021/0011-0486-0100203867 // COMISIONES 00219100248967008054 EMISION TRANSF. CCE 0002520022/0011-0486-0100203867 | Q175: COMISIONES BANCARIAS FEBRERO 2026 | R175: 2026 | S175: 23/02/2026
A176: d | B176: 10410013 BBVA CONTINENTAL MN | C176: 20100130204 | D176: BANCO CONTINENTAL | E176: 03. Pago | F176: 0000000480 | G176: Libro Diario | H176: 46054 | I176: 202602 Febrero 2026 | J176: 12/02/2026 | K176: F FF18-18705855 | L176: F FF18-18705855 | M176: S/ | N176: -4.3 | O176: -4.3 | P176: COMISIONES 00219113140399000050 EMISION TRANSFERENCIA CCE 0002290031/0011-0486-0100203867 | Q176: 12/02 COMISIONES BANCARIAS FEBRERO 2026 | R176: 2026 | S176: 12/02/2026
A177: d | B177: 10410013 BBVA CONTINENTAL MN | C177: 20100130204 | D177: BANCO CONTINENTAL | E177: 03. Pago | F177: 0000000470 | G177: Libro Diario | H177: 46054 | I177: 202602 Febrero 2026 | J177: 06/02/2026 | K177: F FF18-18635897 | L177: F FF18-18635897 | M177: S/ | N177: -4.3 | O177: -4.3 | P177: COMISIONES 00219113765373207158 EMISION TRANSFERENCIA CCE 0002168286/0011-0486-0100203867_x000D_ COMISIONES 00221510413836005727 TRANSFERENCIA BANCARIAS AL BCR 00002168287/011-0486-0100203867_x000D_ COMISIONES 00221510413836005727 TRANSFERNCIAS BANCARIAS AL BCR 00002168287/0011-0486-0100203867_x000D_ COMISIONES 00219113515728000253 EMISION TRANSFERENCIA CCE 00021628285/0011-0486-0100203867 | Q177: 06/02 COMISIONES BANCARIAS FEBRERO 2026 | R177: 2026 | S177: 06/02/2026
A178: d | B178: 10410013 BBVA CONTINENTAL MN | C178: 20100130204 | D178: BANCO CONTINENTAL | E178: 03. Pago | F178: 0000000472 | G178: Libro Diario | H178: 46054 | I178: 202602 Febrero 2026 | J178: 06/02/2026 | K178: F FF18-18635897 | L178: F FF18-18635897 | M178: S/ | N178: -4.3 | O178: -4.3 | P178: COMISIONES 00219113765373207158 EMISION TRANSFERENCIA CCE 0002168286/0011-0486-0100203867_x000D_ COMISIONES 00221510413836005727 TRANSFERENCIA BANCARIAS AL BCR 00002168287/011-0486-0100203867_x000D_ COMISIONES 00221510413836005727 TRANSFERNCIAS BANCARIAS AL BCR 00002168287/0011-0486-0100203867_x000D_ COMISIONES 00219113515728000253 EMISION TRANSFERENCIA CCE 00021628285/0011-0486-0100203867 | Q178: 06/02 COMISIONES BANCARIAS FEBRERO 2026 | R178: 2026 | S178: 06/02/2026
... A251: d | B251: 10410013 BBVA CONTINENTAL MN | C251: 20510934611 | D251: GALVEZ & DOLORIER ABOGADOS S. CIVIL.R.L | E251: 03. Pago | F251: 0000000204 | G251: Libro Diario | H251: 46054 | I251: 202602 Febrero 2026 | J251: 05/02/2026 | K251: F E001-00008252 | L251: F E001-00008252 | M251: S/ | N251: -1439 | O251: -1439 | P251: ASESORIA TRIBUTARIA Y COORPORATIVA NOVIEMBRE 2025. | Q251: PAGO DE DETRACCIONES | R251: 2026 | S251: 05/02/2026
A252: d | B252: 10410013 BBVA CONTINENTAL MN | C252: 10000620471 | D252: VELASQUEZ URREGO, JUAN CARLOS | E252: 03. Pago | F252: 0000000549 | G252: Libro Diario | H252: 46054 | I252: 202602 Febrero 2026 | J252: 26/02/2026 | M252: S/ | N252: -1314.5 | O252: -1314.5 | P252: 26/02 PAGO REEMBOLSO JCV | Q252: 26/02 PAGO REEMBOLSO JCV | R252: 2026 | S252: 26/02/2026
A253: d | B253: 10410013 BBVA CONTINENTAL MN | C253: 20332970411 | D253: PACIFICO COMPAÑIA DE SEGUROS Y REASEGUROS | E253: 03. Pago | F253: 0000000513 | G253: Libro Diario | H253: 46054 | I253: 202602 Febrero 2026 | J253: 12/02/2026 | K253: AP 0000000268 | L253: AP 0000000268 | M253: S/ | N253: -1185.09 | O253: -1185.09 | P253: VIDA LEY FEBRERO 26 - F050-1980806 | Q253: 12/02 PAGO A PROVEEDORES: SERVICIOS | R253: 2026 | S253: 12/02/2026
A254: d | B254: 10410013 BBVA CONTINENTAL MN | C254: 10097521889 | D254: GOMERO ROJAS, GUILLERMO ALBERTO | E254: 03. Pago | F254: 0000000524 | G254: Libro Diario | H254: 46054 | I254: 202602 Febrero 2026 | J254: 23/02/2026 | K254: PR 0000000625 | L254: PR 0000000625 | M254: S/ | N254: -939.5 | O254: -939.5 | P254: DEV. PRESTAMO DE GG (RB CM) | Q254: 23/02 DEVOLUCION DE PRESTAMO GG | R254: 2026 | S254: 23/02/2026
A255: d | B255: 10410013 BBVA CONTINENTAL MN | C255: 20517182673 | D255: MAPFRE PERU S.A. ENTIDAD PRESTADORA DE SALUD | E255: 03. Pago | F255: 0000000507 | G255: Libro Diario | H255: 46054 | I255: 202602 Febrero 2026 | J255: 12/02/2026 | K255: AP 0000000266 | L255: AP 0000000266 | M255: S/ | N255: -853.62 | O255: -853.62 | P255: SEGUROS MAPFRE | Q255: 12/02 PAGO A PROVEEDORES: SERVICIOS | R255: 2026 | S255: 12/02/2026
A256: d | B256: 10410013 BBVA CONTINENTAL MN | C256: 20517182673 | D256: MAPFRE PERU S.A. ENTIDAD PRESTADORA DE SALUD | E256: 03. Pago | F256: 0000000545 | G256: Libro Diario | H256: 46054 | I256: 202602 Febrero 2026 | J256: 26/02/2026 | K256: AP 0000000274 | L256: AP 0000000274 | M256: S/ | N256: -853.62 | O256: -853.62 | P256: SEGUROS MAPFRE F050-616336 | Q256: 26/02 PAGO SEGURO MAPFRE | R256: 2026 | S256: 26/02/2026
A257: d | B257: 10410013 BBVA CONTINENTAL MN | C257: 20474697593 | D257: VINATEA Y TOYAMA ABOG.SOC.CIVIL DE R.L. | E257: 03. Pago | F257: 0000000206 | G257: Libro Diario | H257: 46054 | I257: 202602 Febrero 2026 | J257: 05/02/2026 | K257: F F002-00022646 | L257: F F002-00022646 | M257: S/ | N257: -833 | O257: -833 | P257: SERVICIOS PROFESIONALES DE ASESORIA LEGAL - INFORME | Q257: PAGO DE DETRACCIONES | R257: 2026 | S257: 05/02/2026
A258: d | B258: 10410013 BBVA CONTINENTAL MN | D258: ROSALES PUENTE, YANIRA ANAIS | E258: 03. Pago | F258: 0000000557 | G258: Libro Diario | H258: 46054 | I258: 202602 Febrero 2026 | J258: 12/02/2026 | M258: S/ | N258: -793.76 | O258: -793.76 | P258: 12/02 REEMBOLSO DE CAJA CHICA | Q258: 12/02 REEMBOLSO DE CAJA CHICA | R258: 2026 | S258: 12/02/2026
A259: d | B259: 10410013 BBVA CONTINENTAL MN | C259: 20418896915 | D259: MAPFRE PERU COMPAÑIA DE SEGUROS Y REASEGUROS | E259: 03. Pago | F259: 0000000508 | G259: Libro Diario | H259: 46054 | I259: 202602 Febrero 2026 | J259: 12/02/2026 | K259: AP 0000000267 | L259: AP 0000000267 | M259: S/ | N259: -629.85 | O259: -629.85 | P259: SEGUROS MAPFRE F050-756021 | Q259: 12/02 PAGO A PROVEEDORES: SERVICIOS | R259: 2026 | S259: 12/02/2026
A260: d | B260: 10410013 BBVA CONTINENTAL MN | C260: 20418896915 | D260: MAPFRE PERU COMPAÑIA DE SEGUROS Y REASEGUROS | E260: 03. Pago | F260: 0000000546 | G260: Libro Diario | H260: 46054 | I260: 202602 Febrero 2026 | J260: 26/02/2026 | K260: AP 0000000275 | L260: AP 0000000275 | M260: S/ | N260: -629.85 | O260: -629.85 | P260: SEGUROS MAPFRE F050-00756021 | Q260: 26/02 PAGO SEGURO MAPFRE | R260: 2026 | S260: 26/02/2026
A261: d | B261: 10410013 BBVA CONTINENTAL MN | C261: 10701398420 | D261: BASTIDAS VALDIVIA, JIMY MARLON | E261: 03. Pago | F261: 0000000531 | G261: Libro Diario | H261: 46054 | I261: 202602 Febrero 2026 | J261: 24/02/2026 | K261: ER 0000000218 | L261: ER 0000000218 | M261: S/ | N261: -600 | O261: -600 | P261: ENTREGA A RENDIR - VIAJE CANTA CRBC | Q261: 24/02 ENTREGA A RENDIR | R261: 2026 | S261: 24/02/2026
A262: d | B262: 10410013 BBVA CONTINENTAL MN | C262: 10000620471 | D262: VELASQUEZ URREGO, JUAN CARLOS | E262: 03. Pago | F262: 0000000549 | G262: Libro Diario | H262: 46054 | I262: 202602 Febrero 2026 | J262: 26/02/2026 | M262: S/ | N262: -600 | O262: -600 | P262: 26/02 PAGO REEMBOLSO JCV | Q262: 26/02 PAGO REEMBOLSO JCV | R262: 2026 | S262: 26/02/2026
A263: d | B263: 10410013 BBVA CONTINENTAL MN | C263: 20131367423 | D263: MUNICIPALIDAD SANTIAGO DE SURCO | E263: 03. Pago | F263: 0000000551 | G263: Libro Diario | H263: 46054 | I263: 202602 Febrero 2026 | J263: 26/02/2026 | K263: DP 0000000984 | L263: DP 0000000984 | M263: S/ | N263: -551.57 | O263: -551.57 | P263: ARBITRIOS OFICINA 1302 - AÑO 2026 RECIBO N° 2260293621 | Q263: 26/02 PAGO A PROVEEDORES MUNICIPALIDAD | R263: 2026 | S263: 26/02/2026
A264: d | B264: 10410013 BBVA CONTINENTAL MN | C264: 20131367423 | D264: MUNICIPALIDAD SANTIAGO DE SURCO | E264: 03. Pago | F264: 0000000552 | G264: Libro Diario | H264: 46054 | I264: 202602 Febrero 2026 | J264: 26/02/2026 | K264: DP 0000000984 | L264: DP 0000000984 | M264: S/ | N264: -551.57 | O264: -551.57 | P264: ARBITRIOS OFICINA 1302 - AÑO 2026 RECIBO N° 2260293621 | Q264: 26/02 PAGO A PROVEEDORES MUNICIPALIDAD | R264: 2026 | S264: 26/02/2026
A265: d | B265: 10410013 BBVA CONTINENTAL MN | C265: 20536612972 | D265: CMO GROUP S.A. | E265: 03. Pago | F265: 0000000578 | G265: Libro Diario | H265: 46054 | I265: 202602 Febrero 2026 | J265: 26/02/2026 | K265: PR 0000000636 | L265: PR 0000000636 | M265: S/ | N265: -514.72 | O265: -514.72 | P265: PRESTAMO A CMO // ARBITRIOS 1304 | Q265: 26/02 PRESTAMO A CMO PAGOS VARIOS | R265: 2026 | S265: 26/02/2026
A266: d | B266: 10410013 BBVA CONTINENTAL MN | C266: 20536612972 | D266: CMO GROUP S.A. | E266: 03. Pago | F266: 0000000579 | G266: Libro Diario | H266: 46054 | I266: 202602 Febrero 2026 | J266: 26/02/2026 | K266: PR 0000000636 | L266: PR 0000000636 | M266: S/ | N266: -514.72 | O266: -514.72 | P266: PRESTAMO A CMO // ARBITRIOS 1304 | Q266: 26/02 PRESTAMO A CMO ARBITRIOS | R266: 2026 | S266: 26/02/2026
A267: d | B267: 10410013 BBVA CONTINENTAL MN | C267: 10422397596 | D267: TALLEDO GILVONIO MANUEL OMAR | E267: 03. Pago | F267: 0000000199 | G267: Libro Diario | H267: 46054 | I267: 202602 Febrero 2026 | J267: 05/02/2026 | K267: F E001-00000025 | L267: F E001-00000025 | M267: S/ | N267: -439 | O267: -439 | P267: DISEÑO DE CUADROS // FOTOGRAFÍA DE ALTA RESOLUCIÓN IMPRESAS DE PROYECTOS DE IC// GASTOS VARIOS - OFICINA DE IC | Q267: PAGO DE DETRACCIONES | R267: 2026 | S267: 05/02/2026
A268: d | B268: 10410013 BBVA CONTINENTAL MN | C268: 10404924376 | D268: SILVA AEDO, CHRISTIAN ALEXIS | E268: 03. Pago | F268: 0000000210 | G268: Libro Diario | H268: 46054 | I268: 202602 Febrero 2026 | J268: 05/02/2026 | K268: F E001-00000043 | L268: F E001-00000043 | M268: S/ | N268: -425 | O268: -425 | P268: PRODUCCION DE VIDEO CORPORATIVO POR FIESTAS DE FIN DE AÑO 2025 | Q268: PAGO DE DETRACCIONES | R268: 2026 | S268: 05/02/2026
A269: d | B269: 10410013 BBVA CONTINENTAL MN | C269: 20552504641 | D269: ON EMPRESAS S.A.C. | E269: 03. Pago | F269: 0000000535 | G269: Libro Diario | H269: 46054 | I269: 202602 Febrero 2026 | J269: 24/02/2026 | K269: AP 0000000270 | L269: AP 0000000270 | M269: S/ | N269: -409.9 | O269: -409.9 | P269: SERVICIO FEBRERO RECIBO NRO S006-146649 | Q269: 24/02 PAGO SEGURO FOLA | R269: 2026 | S269: 24/02/2026
A270: d | B270: 10410013 BBVA CONTINENTAL MN | C270: 10422397596 | D270: TALLEDO GILVONIO MANUEL OMAR | E270: 03. Pago | F270: 0000000195 | G270: Libro Diario | H270: 46054 | I270: 202602 Febrero 2026 | J270: 05/02/2026 | K270: F E001-00000020 | L270: F E001-00000020 | M270: S/ | N270: -305 | O270: -305 | P270: MANEJO DE REDES SOCIALES NOVIEMBRE_DICIEMBRE 2025 | Q270: PAGO DE DETRACCIONES | R270: 2026 | S270: 05/02/2026
...

Sheet Detalle S10_Junio 2026 (3)
A1: Item | B1: Cuenta Contable | C1: RUC Socio de Negocio | D1: Socio de Negocio | E1: Procedencia | F1: N° Asiento | G1: Libro | H1: Mes | I1: Periodo Contable | J1: Fecha de Transacción | K1: N° Documento | L1: N° Documento Pago | M1: MO | N1: Saldo Origen | O1: Saldo ( S/ ) | P1: Observación Documento | Q1: Observación | R1: Año | S1: F.Emisión
A2: b | B2: 10410014 BBVA CONTINENTAL ME | D2: YUPANQUI ARTADI, REYNALDO RICARDO | E2: 02. Transferencia a cuenta bancaria | F2: 0000002098 | G2: Caja y Bancos | H2: 46023 | I2: 202601 Enero 2026 | J2: 26/01/2026 | K2: PR 0000000607 | L2: PR 0000000607 | M2: U$ | N2: 45000 | O2: 151155 | P2: PRESTAMO DE REYNALDO A INTEGRAL | Q2: Transferencia a Cuenta Bancaria | R2: 2026 | S2: 26/01/2026
A3: b | B3: 10410014 BBVA CONTINENTAL ME | D3: YUPANQUI ARTADI, REYNALDO RICARDO | E3: 02. Transferencia a cuenta bancaria | F3: 0000002099 | G3: Caja y Bancos | H3: 46023 | I3: 202601 Enero 2026 | J3: 26/01/2026 | K3: PR 0000000608 | L3: PR 0000000608 | M3: U$ | N3: 45000 | O3: 151155 | P3: PRESTAMO DE REYNALDO A INTEGRAL | Q3: Transferencia a Cuenta Bancaria | R3: 2026 | S3: 26/01/2026
A4: b | B4: 10410013 BBVA CONTINENTAL MN | D4: YUPANQUI ARTADI, REYNALDO RICARDO | E4: 02. Transferencia a cuenta bancaria | F4: 0000002090 | G4: Caja y Bancos | H4: 46023 | I4: 202601 Enero 2026 | J4: 19/01/2026 | K4: PR 0000000589 | L4: PR 0000000589 | M4: S/ | N4: 105000 | O4: 105000 | P4: PRESTAMO DE RY ( ICYS) | Q4: PRESTAMO DE ICYS RY | R4: 2026 | S4: 19/01/2026
A5: b | B5: 10410014 BBVA CONTINENTAL ME | D5: YUPANQUI ARTADI, REYNALDO RICARDO | E5: 02. Transferencia a cuenta bancaria | F5: 0000000609 | G5: Caja y Bancos | H5: 46054 | I5: 202602 Febrero 2026 | J5: 07/02/2026 | K5: PR 0000000639 | L5: PR 0000000639 | M5: U$ | N5: 11850 | O5: 39851.55 | P5: PRESTAMO DE REYNALDO A INTEGRAL | Q5: PRESTAMO DE RY | R5: 2026 | S5: 07/02/2026
A6: b | B6: 10410013 BBVA CONTINENTAL MN | C6: 10415120911 | D6: GUTIERREZ ACQUARONE, GUSTAVO | E6: 02. Transferencia a cuenta bancaria | F6: 0000000605 | G6: Caja y Bancos | H6: 46054 | I6: 202602 Febrero 2026 | J6: 17/02/2026 | K6: DEV 0000000018 | L6: DEV 0000000018 | M6: S/ | N6: 204 | O6: 204 | P6: DEVOLUCION DE ER GG | Q6: DEVOLUCION DE ER | R6: 2026 | S6: 17/02/2026
A7: b | B7: 10410014 BBVA CONTINENTAL ME | E7: 14. Diferencia de cambio - Cuentas | F7: 0000000380 | G7: Diferencia de Cambio | H7: 46054 | I7: 202602 Febrero 2026 | J7: 28/02/2026 | M7: U$ | N7: 0 | O7: 439.12 | P7: Diferencia de cambio - Por Cuenta | Q7: Diferencia de cambio - Por Cuenta | R7: 2026 | S7: 28/02/2026
A8: b | B8: 10410013 BBVA CONTINENTAL MN | C8: 10074121395 | D8: JONES PATRONI, GUILLERMO AUGUSTO | E8: 02. Transferencia a cuenta bancaria | F8: 0000000876 | G8: Caja y Bancos | H8: 46082 | I8: 202603 Marzo 2026 | J8: 13/03/2026 | K8: DEV 0000000019 | L8: DEV 0000000019 | M8: S/ | N8: 3.12 | O8: 3.12 | P8: DEVOLUCION DE ER WILLY JONES | Q8: Transferencia a Cuenta Bancaria | R8: 2026 | S8: 13/03/2026
A9: b | B9: 10410014 BBVA CONTINENTAL ME | C9: 20536612972 | D9: CMO GROUP S.A. | E9: 02. Transferencia a cuenta bancaria | F9: 0000000822 | G9: Caja y Bancos | H9: 46082 | I9: 202603 Marzo 2026 | J9: 04/03/2026 | K9: DP 0000000030 | L9: DP 0000000030 | M9: U$ | N9: 95948 | O9: 326990.78 | P9: INGRESOS DE CMO SEGUN EECC (O.PAGO REC EXT LIQ:9675785) | Q9: INGRESOS CMO | R9: 2026 | S9: 04/03/2026
A10: b | B10: 10410014 BBVA CONTINENTAL ME | E10: 14. Diferencia de cambio - Cuentas | F10: 0000000485 | G10: Diferencia de Cambio | H10: 46082 | I10: 202603 Marzo 2026 | J10: 31/03/2026 | M10: U$ | N10: 0 | O10: 140.3 | P10: Diferencia de cambio - Por Cuenta | Q10: Diferencia de cambio - Por Cuenta | R10: 2026 | S10: 31/03/2026
A11: b | B11: 10410013 BBVA CONTINENTAL MN | C11: 20602384714 | D11: ICYS S.A.C. | E11: 02. Transferencia a cuenta bancaria | F11: 0000003067 | G11: Caja y Bancos | H11: 46113 | I11: 202604 Abril 2026 | J11: 30/04/2026 | K11: PR 0000000694 | L11: PR 0000000694 | M11: S/ | N11: 213000 | O11: 213000 | P11: PRESTAMO RECIBIDO DE ICYS // PARA EL PAGO DE SUNAT IMPUESTO PRICO IGV, PRESTAMO A CMO, ETC | Q11: PRESTAMO RECIBIDO DE ICYS | R11: 2026 | S11: 30/04/2026
A12: b | B12: 10410014 BBVA CONTINENTAL ME | E12: 14. Diferencia de cambio - Cuentas | F12: 0000002966 | G12: Diferencia de Cambio | H12: 46113 | I12: 202604 Abril 2026 | J12: 30/04/2026 | M12: U$ | N12: 0 | O12: 85.26 | P12: Diferencia de cambio - Por Cuenta | Q12: Diferencia de cambio - Por Cuenta | R12: 2026 | S12: 30/04/2026
A13: b | B13: 10410013 BBVA CONTINENTAL MN | D13: YUPANQUI ARTADI, REYNALDO RICARDO | E13: 02. Transferencia a cuenta bancaria | F13: 0000003378 | G13: Caja y Bancos | H13: 46143 | I13: 202605 Mayo 2026 | J13: 29/05/2026 | K13: PR 0000000727 | L13: PR 0000000727 | M13: S/ | N13: 275240 | O13: 275240 | P13: PRESTAMO DE RY | Q13: PRESTAMO RECIBIDO DE RY | R13: 2026 | S13: 29/05/2026
A14: b | B14: 10410013 BBVA CONTINENTAL MN | C14: 20602384714 | D14: ICYS S.A.C. | E14: 02. Transferencia a cuenta bancaria | F14: 0000003417 | G14: Caja y Bancos | H14: 46143 | I14: 202605 Mayo 2026 | J14: 08/05/2026 | K14: PR 0000000728 | L14: PR 0000000728 | M14: S/ | N14: 76100 | O14: 76100 | P14: PRESTAMO RECIBIDO DE ICYS | Q14: PRÉSTAMO DE ICYS | R14: 2026 | S14: 08/05/2026
A15: b | B15: 10410013 BBVA CONTINENTAL MN | C15: 20536612972 | D15: CMO GROUP S.A. | E15: 02. Transferencia a cuenta bancaria | F15: 0000003548 | G15: Caja y Bancos | H15: 46143 | I15: 202605 Mayo 2026 | J15: 13/05/2026 | K15: DP 0000000033 | L15: DP 0000000033 | M15: S/ | N15: 500000 | O15: 500000 | P15: INGRESOS DE CMO - CONSORCIO JULI | Q15: INGRESOS DE CMO - (C - JULY) | R15: 2026 | S15: 13/05/2026
A16: b | B16: 10410013 BBVA CONTINENTAL MN | C16: 20600964608 | D16: SERVICIOS GENERALES DE CONSTRUCCION C & C S.A.C. | E16: 02. Transferencia a cuenta bancaria | F16: 0000003583 | G16: Caja y Bancos | H16: 46143 | I16: 202605 Mayo 2026 | J16: 26/05/2026 | K16: DP 0000000034 | L16: DP 0000000034 | M16: S/ | N16: 48 | O16: 48 | P16: DEVOLUCION POR PAGO EN EXCESO MULTISERVIS E001-292 | Q16: DEVOLUCION DE PAGO EN EXCESO MULTISERVIS | R16: 2026 | S16: 26/05/2026
A17: b | B17: 10410013 BBVA CONTINENTAL MN | C17: 20601402409 | D17: PRODUCTOS Y SERVICIOS SILVA QUEVEDO E.I.R.L. | E17: 02. Transferencia a cuenta bancaria | F17: 0000003419 | G17: Caja y Bancos | H17: 46143 | I17: 202605 Mayo 2026 | J17: 01/05/2026 | K17: DEV 0000000020 | L17: DEV 0000000020 | M17: S/ | N17: 100 | O17: 100 | P17: DEVOLUCION POR GARANNTIA - APERITIVOS DIA DEL TRABAJADOR | Q17: ABONO INMEDIATO 002 JUAN PIO SILVA CAS DEVOLUCIÓN DE LA GARANTÍA (KISU) | R17: 2026 | S17: 01/05/2026
A18: b | B18: 10410013 BBVA CONTINENTAL MN | C18: 10704539237 | D18: CUYUBAMBA SOTO, ARAMIS GABRIEL | E18: 02. Transferencia a cuenta bancaria | F18: 0000003240 | G18: Caja y Bancos | H18: 46143 | I18: 202605 Mayo 2026 | J18: 21/05/2026 | K18: DEV 0000000021 | L18: DEV 0000000021 | M18: S/ | N18: 104.17 | O18: 104.17 | P18: DEVOLUCION DE VIATICOS POR VIAJE A CHOTA DEL 07 AL 08 DE MAYO | Q18: Transferencia a Cuenta Bancaria | R18: 2026 | S18: 21/05/2026
A19: b | B19: 10410013 BBVA CONTINENTAL MN | C19: 20605171941 | D19: CHINA ROAD AND BRIDGE CORPORATION SUCURSAL PERU | E19: 02. Transferencia a cuenta bancaria | F19: 0000003479 | G19: Caja y Bancos | H19: 46143 | I19: 202605 Mayo 2026 | J19: 08/05/2026 | K19: PR 0000000594 | L19: PR 0000000594 | M19: S/ | N19: 2496.88 | O19: 2496.88 | P19: PRESTAMO A CRBC POR VIAJE DE COMISION DE SERVICIOS DE LA OBRA DE CHOTA/ GUILLERMO JONES Y ARAMIS CUYUBAMBA DEL 23 AL 25.02.2026 | Q19: COBRANZA DE PRESTAMO | R19: 2026 | S19: 11/03/2026
A20: b | B20: 10410013 BBVA CONTINENTAL MN | D20: YUPANQUI ARTADI, REYNALDO RICARDO | E20: 02. Transferencia a cuenta bancaria | F20: 0000003859 | G20: Caja y Bancos | H20: 0000000001 | I20: 202606 Junio 2026 | J20: 02/06/2026 | K20: PR 0000000743 | L20: PR 0000000743 | M20: S/ | N20: 51000 | O20: 51000 | P20: PRESTAMO DE RY | Q20: PRESTAMO RECIBIDO PR 743 | R20: 2026 | S20: 02/06/2026
A21: b | B21: 10410013 BBVA CONTINENTAL MN | C21: 20100130204 | D21: BANCO CONTINENTAL | E21: 03. Pago | F21: 0000003925 | G21: Libro Diario | H21: 000000000107 | I21: 202606 Junio 2026 | J21: 09/06/2026 | K21: TR 0000000107 | L21: TR 0000000107 | M21: S/ | N21: -58951.26 | O21: -58951.26 | P21: TRANSFERENCIA DE FONDOS A CUENTA SOLES ADM | Q21: TRANSFERENCIA DE FONDOS A CUENTA SOLES ADM | R21: 2026 | S21: 09/06/2026
A22: b | B22: 10410013 BBVA CONTINENTAL MN | C22: 20536612972 | D22: CMO GROUP S.A. | E22: 02. Transferencia a cuenta bancaria | F22: 0000004005 | G22: Caja y Bancos | H22: 0000000001 | I22: 202606 Junio 2026 | J22: 09/06/2026 | K22: DP 0000000035 | L22: DP 0000000035 | M22: S/ | N22: 59637.25 | O22: 59637.25 | P22: INGRESOS DE CMO | Q22: INGRESOS DE CMO | R22: 2026 | S22: 09/06/2026
A23: b | B23: 10410013 BBVA CONTINENTAL MN | D23: YUPANQUI ARTADI, REYNALDO RICARDO | E23: 02. Transferencia a cuenta bancaria | F23: 0000004012 | G23: Caja y Bancos | H23: 0000000001 | I23: 202606 Junio 2026 | J23: 30/06/2026 | K23: PR 0000000752 | L23: PR 0000000752 | M23: S/ | N23: 182000 | O23: 182000 | P23: PRESTAMO DE RY | Q23: PRESTAMO RECIBIDO RY | R23: 2026 | S23: 30/06/2026
O24: =SUM(O2:O23) -> 2075799.2
K27: RY | O27: 955402
K28: OTROS | O28: -55630
K29: CMO | O29: 886628
K30: ICYS | O30: 289100
O31: =SUBTOTAL(9,O27:O30) -> 2075500

Sheet Hoja2
B3: CMO | C3: -1505086.9
